[
    {
        "id": "SVJP-001",
        "cardID": "펄기물220영역000하이200",
        "name": "오리진 펄기아 V",
        "supertype": "포켓몬",
        "subtypes": [
            "기본",
            "V"
        ],
        "rules": [
            "포켓몬 V가 기절한 경우 상대는 프라이즈를 2장 가져간다."
        ],
        "hp": 220,
        "pokemons": [
            {
                "name": "펄기아",
                "pokedexNumber": 484
            }
        ],
        "type": "(물)",
        "attacks": [
            {
                "name": "영역지배",
                "cost": "(물)",
                "damage": "",
                "text": "자신의 덱에서 스타디움을 1장 선택해서 상대에게 보여주고 패로 가져온다. 그리고 덱을 섞는다."
            },
            {
                "name": "하이드로 브레이크",
                "cost": "(물)(물)(무색)",
                "damage": "200",
                "text": "자신의 다음 차례에 이 포켓몬은 기술을 사용할 수 없다."
            }
        ],
        "abilities": [],
        "weakness": {
            "type": "(번개)",
            "value": "×2"
        },
        "resistance": {
            "type": "",
            "value": "--"
        },
        "retreatCost": 2,
        "flavorText": "",
        "number": "001",
        "prodNumber": "019",
        "prodCode": "SVJP",
        "prodSymbolURL": "https://cards.image.pokemonkorea.co.kr/data/images/symbol/SVJP.png",
        "prodName": "스칼렛&바이올렛 배틀 마스터 덱 「파오젠 ex」",
        "artist": "aky CG Works",
        "rarity": "N",
        "regulationMark": "F",
        "cardImgURL": "https://cards.image.pokemonkorea.co.kr/data/wmimages/SV/SVJP/SVJP_001.png?w=512",
        "cardPageURL": "https://pokemoncard.co.kr/cards/detail/BS2024010001"
    },
    {
        "id": "SVJP-002",
        "cardID": "펄기물280스타공간060",
        "name": "오리진 펄기아 VSTAR",
        "supertype": "포켓몬",
        "subtypes": [
            "V진화",
            "VSTAR"
        ],
        "rules": [
            "포켓몬 VSTAR가 기절한 경우 상대는 프라이즈를 2장 가져간다."
        ],
        "hp": 280,
        "pokemons": [
            {
                "name": "펄기아",
                "pokedexNumber": 484
            }
        ],
        "type": "(물)",
        "attacks": [
            {
                "name": "공간의너울",
                "cost": "(물)(물)",
                "damage": "60+",
                "text": "서로의 벤치 포켓몬의 수 × 20데미지를 추가한다."
            }
        ],
        "abilities": [
            {
                "name": "스타포털",
                "text": "자신의 차례에 사용할 수 있다. 자신의 트래쉬에서 (물) 에너지를 3장까지 선택해서 자신의 (물) 포켓몬에게 원하는 대로 붙인다. (대전 중 자신은 VSTAR 파워를 1번만 사용할 수 있다.)",
                "type": "특성",
                "special": "VSTAR"
            }
        ],
        "weakness": {
            "type": "(번개)",
            "value": "×2"
        },
        "resistance": {
            "type": "",
            "value": "--"
        },
        "retreatCost": 2,
        "flavorText": "",
        "number": "002",
        "prodNumber": "019",
        "prodCode": "SVJP",
        "prodSymbolURL": "https://cards.image.pokemonkorea.co.kr/data/images/symbol/SVJP.png",
        "prodName": "스칼렛&바이올렛 배틀 마스터 덱 「파오젠 ex」",
        "artist": "aky CG Works",
        "rarity": "N",
        "regulationMark": "F",
        "cardImgURL": "https://cards.image.pokemonkorea.co.kr/data/wmimages/SV/SVJP/SVJP_002.png?w=512",
        "cardPageURL": "https://pokemoncard.co.kr/cards/detail/BS2024010002"
    },
    {
        "id": "SVJP-003",
        "cardID": "개굴물130숨겨월광000",
        "name": "찬란한 개굴닌자",
        "supertype": "포켓몬",
        "subtypes": [
            "기본",
            "찬란한"
        ],
        "rules": [
            "찬란한 포켓몬은 덱에 1장만 넣을 수 있다."
        ],
        "hp": 130,
        "pokemons": [
            {
                "name": "개굴닌자",
                "pokedexNumber": 658
            }
        ],
        "type": "(물)",
        "attacks": [
            {
                "name": "월광수리검",
                "cost": "(물)(물)(무색)",
                "damage": "",
                "text": "이 포켓몬에게 붙어 있는 에너지를 2개 트래쉬하고 상대의 포켓몬 2마리에게 각각 90데미지를 준다. (벤치는 약점, 저항력 계산을 하지 않는다.)"
            }
        ],
        "abilities": [
            {
                "name": "숨겨진 수단",
                "text": "자신의 차례에 자신의 패에서 에너지를 1장 트래쉬한다면 1번 사용할 수 있다. 자신의 덱을 2장 뽑는다.",
                "type": "특성"
            }
        ],
        "weakness": {
            "type": "(번개)",
            "value": "×2"
        },
        "resistance": {
            "type": "",
            "value": "--"
        },
        "retreatCost": 1,
        "flavorText": "닌자처럼 신출귀몰하다. 재빠른 움직임으로 상대를 농락하면서 물의 수리검으로 벤다.",
        "number": "003",
        "prodNumber": "019",
        "prodCode": "SVJP",
        "prodSymbolURL": "https://cards.image.pokemonkorea.co.kr/data/images/symbol/SVJP.png",
        "prodName": "스칼렛&바이올렛 배틀 마스터 덱 「파오젠 ex」",
        "artist": "Souichirou Gunjima",
        "rarity": "N",
        "regulationMark": "F",
        "cardImgURL": "https://cards.image.pokemonkorea.co.kr/data/wmimages/SV/SVJP/SVJP_003.png?w=512",
        "cardPageURL": "https://pokemoncard.co.kr/cards/detail/BS2024010003"
    },
    {
        "id": "SVJP-004",
        "cardID": "드니물060몸통030",
        "name": "드니차",
        "supertype": "포켓몬",
        "subtypes": [
            "기본"
        ],
        "rules": [],
        "hp": 60,
        "pokemons": [
            {
                "name": "드니차",
                "pokedexNumber": 996
            }
        ],
        "type": "(물)",
        "attacks": [
            {
                "name": "몸통박치기",
                "cost": "(물)(무색)",
                "damage": "30",
                "text": ""
            }
        ],
        "abilities": [],
        "weakness": {
            "type": "(강철)",
            "value": "×2"
        },
        "resistance": {
            "type": "",
            "value": "--"
        },
        "retreatCost": 1,
        "flavorText": "등지느러미로 열을 흡수해서 얼음 에너지로 변환한다. 고온일수록 에너지가 많이 모인다.",
        "number": "004",
        "prodNumber": "019",
        "prodCode": "SVJP",
        "prodSymbolURL": "https://cards.image.pokemonkorea.co.kr/data/images/symbol/SVJP.png",
        "prodName": "스칼렛&바이올렛 배틀 마스터 덱 「파오젠 ex」",
        "artist": "Akira Komayama",
        "rarity": "N",
        "regulationMark": "G",
        "cardImgURL": "https://cards.image.pokemonkorea.co.kr/data/wmimages/SV/SVJP/SVJP_004.png?w=512",
        "cardPageURL": "https://pokemoncard.co.kr/cards/detail/BS2024010004"
    },
    {
        "id": "SVJP-005",
        "cardID": "드니물090날카040프로080",
        "name": "드니꽁",
        "supertype": "포켓몬",
        "subtypes": [
            "1진화"
        ],
        "rules": [],
        "hp": 90,
        "pokemons": [
            {
                "name": "드니꽁",
                "pokedexNumber": 997
            }
        ],
        "type": "(물)",
        "attacks": [
            {
                "name": "날카로운 지느러미",
                "cost": "(물)(무색)",
                "damage": "40",
                "text": ""
            },
            {
                "name": "프로스트 스매시",
                "cost": "(물)(물)(무색)",
                "damage": "80",
                "text": ""
            }
        ],
        "abilities": [],
        "weakness": {
            "type": "(강철)",
            "value": "×2"
        },
        "resistance": {
            "type": "",
            "value": "--"
        },
        "retreatCost": 2,
        "flavorText": "주변의 공기를 얼려서 얼음 마스크로 얼굴을 보호하고 등지느러미를 얼음 검으로 바꾼다.",
        "number": "005",
        "prodNumber": "019",
        "prodCode": "SVJP",
        "prodSymbolURL": "https://cards.image.pokemonkorea.co.kr/data/images/symbol/SVJP.png",
        "prodName": "스칼렛&바이올렛 배틀 마스터 덱 「파오젠 ex」",
        "artist": "Kouki Saitou",
        "rarity": "N",
        "regulationMark": "G",
        "cardImgURL": "https://cards.image.pokemonkorea.co.kr/data/wmimages/SV/SVJP/SVJP_005.png?w=512",
        "cardPageURL": "https://pokemoncard.co.kr/cards/detail/BS2024010005"
    },
    {
        "id": "SVJP-006",
        "cardID": "드닐물160극저버스130",
        "name": "드닐레이브",
        "supertype": "포켓몬",
        "subtypes": [
            "2진화"
        ],
        "rules": [],
        "hp": 160,
        "pokemons": [
            {
                "name": "드닐레이브",
                "pokedexNumber": 998
            }
        ],
        "type": "(물)",
        "attacks": [
            {
                "name": "버스터테일",
                "cost": "(물)(물)(무색)",
                "damage": "130",
                "text": ""
            }
        ],
        "abilities": [
            {
                "name": "극저온",
                "text": "자신의 차례에 몇 번이라도 사용할 수 있다. 자신의 패에서 「기본 (물) 에너지」를 1장 선택해서 자신의 포켓몬에게 붙인다.",
                "type": "특성"
            }
        ],
        "weakness": {
            "type": "(강철)",
            "value": "×2"
        },
        "resistance": {
            "type": "",
            "value": "--"
        },
        "retreatCost": 2,
        "flavorText": "극저온의 냉기를 입에서 분사한다. 작열하는 마그마조차도 순식간에 얼려 버린다.",
        "number": "006",
        "prodNumber": "019",
        "prodCode": "SVJP",
        "prodSymbolURL": "https://cards.image.pokemonkorea.co.kr/data/images/symbol/SVJP.png",
        "prodName": "스칼렛&바이올렛 배틀 마스터 덱 「파오젠 ex」",
        "artist": "Shin Nagasawa",
        "rarity": "N",
        "regulationMark": "G",
        "cardImgURL": "https://cards.image.pokemonkorea.co.kr/data/wmimages/SV/SVJP/SVJP_006.png?w=512",
        "cardPageURL": "https://pokemoncard.co.kr/cards/detail/BS2024010006"
    },
    {
        "id": "SVJP-007",
        "cardID": "파오물220부들헤일060",
        "name": "파오젠 ex",
        "supertype": "포켓몬",
        "subtypes": [
            "기본",
            "ex"
        ],
        "rules": [
            "포켓몬 ex가 기절한 경우 상대는 프라이즈를 2장 가져간다."
        ],
        "hp": 220,
        "pokemons": [
            {
                "name": "파오젠",
                "pokedexNumber": 1002
            }
        ],
        "type": "(물)",
        "attacks": [
            {
                "name": "헤일블레이드",
                "cost": "(물)(물)",
                "damage": "60×",
                "text": "자신의 필드의 포켓몬에게 붙어 있는 (물) 에너지를 원하는 만큼 트래쉬하고 그 장수 × 60데미지를 준다."
            }
        ],
        "abilities": [
            {
                "name": "부들부들 냉기",
                "text": "이 포켓몬이 배틀필드에 있다면 자신의 차례에 1번 사용할 수 있다. 자신의 덱에서 「기본 (물) 에너지」를 2장까지 선택해서 상대에게 보여주고 패로 가져온다. 그리고 덱을 섞는다.",
                "type": "특성"
            }
        ],
        "weakness": {
            "type": "(강철)",
            "value": "×2"
        },
        "resistance": {
            "type": "",
            "value": "--"
        },
        "retreatCost": 2,
        "flavorText": "",
        "number": "007",
        "prodNumber": "019",
        "prodCode": "SVJP",
        "prodSymbolURL": "https://cards.image.pokemonkorea.co.kr/data/images/symbol/SVJP.png",
        "prodName": "스칼렛&바이올렛 배틀 마스터 덱 「파오젠 ex」",
        "artist": "aky CG Works",
        "rarity": "N",
        "regulationMark": "G",
        "cardImgURL": "https://cards.image.pokemonkorea.co.kr/data/wmimages/SV/SVJP/SVJP_007.png?w=512",
        "cardPageURL": "https://pokemoncard.co.kr/cards/detail/BS2024010007"
    },
    {
        "id": "SVJP-008",
        "cardID": "비버무060태연필살030",
        "name": "비버니",
        "supertype": "포켓몬",
        "subtypes": [
            "기본"
        ],
        "rules": [],
        "hp": 60,
        "pokemons": [
            {
                "name": "비버니",
                "pokedexNumber": 399
            }
        ],
        "type": "(무색)",
        "attacks": [
            {
                "name": "필살앞니",
                "cost": "(무색)(무색)",
                "damage": "30",
                "text": "동전을 1번 던져서 뒷면이 나오면 이 기술은 실패한다."
            }
        ],
        "abilities": [
            {
                "name": "태연한 얼굴",
                "text": "이 포켓몬은 벤치에 있는 한, 기술의 데미지를 받지 않는다.",
                "type": "특성"
            }
        ],
        "weakness": {
            "type": "(격투)",
            "value": "×2"
        },
        "resistance": {
            "type": "",
            "value": "--"
        },
        "retreatCost": 1,
        "flavorText": "항상 큰 나무나 돌을 갉아서 튼튼한 앞니를 갈아 내고 있다. 물가에 둥지를 만들어 산다.",
        "number": "008",
        "prodNumber": "019",
        "prodCode": "SVJP",
        "prodSymbolURL": "https://cards.image.pokemonkorea.co.kr/data/images/symbol/SVJP.png",
        "prodName": "스칼렛&바이올렛 배틀 마스터 덱 「파오젠 ex」",
        "artist": "Naoyo Kimura",
        "rarity": "N",
        "regulationMark": "F",
        "cardImgURL": "https://cards.image.pokemonkorea.co.kr/data/wmimages/SV/SVJP/SVJP_008.png?w=512",
        "cardPageURL": "https://pokemoncard.co.kr/cards/detail/BS2024010008"
    },
    {
        "id": "SVJP-009",
        "cardID": "비버무120일하테일100",
        "name": "비버통",
        "supertype": "포켓몬",
        "subtypes": [
            "1진화"
        ],
        "rules": [],
        "hp": 120,
        "pokemons": [
            {
                "name": "비버통",
                "pokedexNumber": 400
            }
        ],
        "type": "(무색)",
        "attacks": [
            {
                "name": "테일스매시",
                "cost": "(무색)(무색)(무색)",
                "damage": "100",
                "text": "동전을 1번 던져서 뒷면이 나오면 이 기술은 실패한다."
            }
        ],
        "abilities": [
            {
                "name": "일하는 앞니",
                "text": "자신의 차례에 1번 사용할 수 있다. 자신의 패가 5장이 되도록 덱을 뽑는다.",
                "type": "특성"
            }
        ],
        "weakness": {
            "type": "(격투)",
            "value": "×2"
        },
        "resistance": {
            "type": "",
            "value": "--"
        },
        "retreatCost": 2,
        "flavorText": "강을 나무줄기나 진흙의 댐으로 막아서 거처를 만든다. 부지런한 일꾼으로 알려져 있다.",
        "number": "009",
        "prodNumber": "019",
        "prodCode": "SVJP",
        "prodSymbolURL": "https://cards.image.pokemonkorea.co.kr/data/images/symbol/SVJP.png",
        "prodName": "스칼렛&바이올렛 배틀 마스터 덱 「파오젠 ex」",
        "artist": "OKACHEKE",
        "rarity": "N",
        "regulationMark": "F",
        "cardImgURL": "https://cards.image.pokemonkorea.co.kr/data/wmimages/SV/SVJP/SVJP_009.png?w=512",
        "cardPageURL": "https://pokemoncard.co.kr/cards/detail/BS2024010009"
    },
    {
        "id": "SVJP-010",
        "cardID": "네스트볼",
        "name": "네스트볼",
        "supertype": "트레이너스",
        "subtypes": [
            "아이템"
        ],
        "rules": [
            "아이템은 자신의 차례에 몇 장이라도 사용할 수 있다."
        ],
        "texts": [
            "자신의 덱에서 기본 포켓몬을 1장 선택해서 벤치로 내보낸다.",
            "그리고 덱을 섞는다."
        ],
        "number": "010",
        "prodNumber": "019",
        "prodCode": "SVJP",
        "prodSymbolURL": "https://cards.image.pokemonkorea.co.kr/data/images/symbol/SVJP.png",
        "prodName": "스칼렛&바이올렛 배틀 마스터 덱 「파오젠 ex」",
        "artist": "Toyste Beach",
        "rarity": "N",
        "regulationMark": "G",
        "cardImgURL": "https://cards.image.pokemonkorea.co.kr/data/wmimages/SV/SVJP/SVJP_010.png?w=512",
        "cardPageURL": "https://pokemoncard.co.kr/cards/detail/BS2024010010"
    },
    {
        "id": "SVJP-011",
        "cardID": "수퍼 에너지 회수",
        "name": "수퍼 에너지 회수",
        "supertype": "트레이너스",
        "subtypes": [
            "아이템"
        ],
        "rules": [
            "아이템은 자신의 차례에 몇 장이라도 사용할 수 있다."
        ],
        "texts": [
            "이 카드는 자신의 패를 2장 트래쉬하지 않으면 사용할 수 없다.",
            "자신의 트래쉬에서 기본 에너지를 4장까지 선택해서 상대에게 보여주고 패로 가져온다.",
            "(이 카드의 효과로 트래쉬한 에너지는 선택할 수 없다.)"
        ],
        "number": "011",
        "prodNumber": "019",
        "prodCode": "SVJP",
        "prodSymbolURL": "https://cards.image.pokemonkorea.co.kr/data/images/symbol/SVJP.png",
        "prodName": "스칼렛&바이올렛 배틀 마스터 덱 「파오젠 ex」",
        "artist": "Studio Bora Inc.",
        "rarity": "N",
        "regulationMark": "G",
        "cardImgURL": "https://cards.image.pokemonkorea.co.kr/data/wmimages/SV/SVJP/SVJP_011.png?w=512",
        "cardPageURL": "https://pokemoncard.co.kr/cards/detail/BS2024010011"
    },
    {
        "id": "SVJP-012",
        "cardID": "이상한사탕",
        "name": "이상한사탕",
        "supertype": "트레이너스",
        "subtypes": [
            "아이템"
        ],
        "rules": [
            "아이템은 자신의 차례에 몇 장이라도 사용할 수 있다."
        ],
        "texts": [
            "자신의 패에서 2진화 포켓몬을 1장 선택해서 그 포켓몬으로 진화하는 자신의 필드의 기본 포켓몬 위에 올려 1진화를 건너뛰어 진화시킨다.",
            "(자신의 첫 번째 차례와 이번 차례에 내보낸 포켓몬에게는 사용할 수 없다.)"
        ],
        "number": "012",
        "prodNumber": "019",
        "prodCode": "SVJP",
        "prodSymbolURL": "https://cards.image.pokemonkorea.co.kr/data/images/symbol/SVJP.png",
        "prodName": "스칼렛&바이올렛 배틀 마스터 덱 「파오젠 ex」",
        "artist": "Studio Bora Inc.",
        "rarity": "N",
        "regulationMark": "G",
        "cardImgURL": "https://cards.image.pokemonkorea.co.kr/data/wmimages/SV/SVJP/SVJP_012.png?w=512",
        "cardPageURL": "https://pokemoncard.co.kr/cards/detail/BS2024010012"
    },
    {
        "id": "SVJP-013",
        "cardID": "포켓몬 교체",
        "name": "포켓몬 교체",
        "supertype": "트레이너스",
        "subtypes": [
            "아이템"
        ],
        "rules": [
            "아이템은 자신의 차례에 몇 장이라도 사용할 수 있다."
        ],
        "texts": [
            "자신의 배틀 포켓몬을 벤치 포켓몬과 교체한다."
        ],
        "number": "013",
        "prodNumber": "019",
        "prodCode": "SVJP",
        "prodSymbolURL": "https://cards.image.pokemonkorea.co.kr/data/images/symbol/SVJP.png",
        "prodName": "스칼렛&바이올렛 배틀 마스터 덱 「파오젠 ex」",
        "artist": "Studio Bora Inc.",
        "rarity": "N",
        "regulationMark": "G",
        "cardImgURL": "https://cards.image.pokemonkorea.co.kr/data/wmimages/SV/SVJP/SVJP_013.png?w=512",
        "cardPageURL": "https://pokemoncard.co.kr/cards/detail/BS2024010013"
    },
    {
        "id": "SVJP-014",
        "cardID": "하이퍼볼",
        "name": "하이퍼볼",
        "supertype": "트레이너스",
        "subtypes": [
            "아이템"
        ],
        "rules": [
            "아이템은 자신의 차례에 몇 장이라도 사용할 수 있다."
        ],
        "texts": [
            "이 카드는 자신의 패를 2장 트래쉬하지 않으면 사용할 수 없다.",
            "자신의 덱에서 포켓몬을 1장 선택해서 상대에게 보여주고 패로 가져온다.",
            "그리고 덱을 섞는다."
        ],
        "number": "014",
        "prodNumber": "019",
        "prodCode": "SVJP",
        "prodSymbolURL": "https://cards.image.pokemonkorea.co.kr/data/images/symbol/SVJP.png",
        "prodName": "스칼렛&바이올렛 배틀 마스터 덱 「파오젠 ex」",
        "artist": "Ayaka Yoshida",
        "rarity": "N",
        "regulationMark": "G",
        "cardImgURL": "https://cards.image.pokemonkorea.co.kr/data/wmimages/SV/SVJP/SVJP_014.png?w=512",
        "cardPageURL": "https://pokemoncard.co.kr/cards/detail/BS2024010014"
    },
    {
        "id": "SVJP-015",
        "cardID": "모야모",
        "name": "모야모",
        "supertype": "트레이너스",
        "subtypes": [
            "서포트"
        ],
        "rules": [
            "서포트는 자신의 차례에 1장만 사용할 수 있다."
        ],
        "texts": [
            "서로의 플레이어는 각각 자신의 패를 모두 뒷면으로 하여 섞고 덱의 아래로 되돌린다.",
            "그 뒤, 각각 자신의 남은 프라이즈 장수만큼 덱을 뽑는다."
        ],
        "number": "015",
        "prodNumber": "019",
        "prodCode": "SVJP",
        "prodSymbolURL": "https://cards.image.pokemonkorea.co.kr/data/images/symbol/SVJP.png",
        "prodName": "스칼렛&바이올렛 배틀 마스터 덱 「파오젠 ex」",
        "artist": "Sanosuke Sakuma",
        "rarity": "N",
        "regulationMark": "G",
        "cardImgURL": "https://cards.image.pokemonkorea.co.kr/data/wmimages/SV/SVJP/SVJP_015.png?w=512",
        "cardPageURL": "https://pokemoncard.co.kr/cards/detail/BS2024010015"
    },
    {
        "id": "SVJP-016",
        "cardID": "박사의 연구",
        "name": "박사의 연구",
        "supertype": "트레이너스",
        "subtypes": [
            "서포트"
        ],
        "rules": [
            "서포트는 자신의 차례에 1장만 사용할 수 있다."
        ],
        "texts": [
            "자신의 패를 모두 트래쉬하고 덱을 7장 뽑는다."
        ],
        "number": "016",
        "prodNumber": "019",
        "prodCode": "SVJP",
        "prodSymbolURL": "https://cards.image.pokemonkorea.co.kr/data/images/symbol/SVJP.png",
        "prodName": "스칼렛&바이올렛 배틀 마스터 덱 「파오젠 ex」",
        "artist": "kirisAki",
        "rarity": "N",
        "regulationMark": "G",
        "cardImgURL": "https://cards.image.pokemonkorea.co.kr/data/wmimages/SV/SVJP/SVJP_016.png?w=512",
        "cardPageURL": "https://pokemoncard.co.kr/cards/detail/BS2024010016"
    },
    {
        "id": "SVJP-017",
        "cardID": "보스의 지령",
        "name": "보스의 지령",
        "supertype": "트레이너스",
        "subtypes": [
            "서포트"
        ],
        "rules": [
            "서포트는 자신의 차례에 1장만 사용할 수 있다."
        ],
        "texts": [
            "상대의 벤치 포켓몬을 1마리 선택해서 배틀 포켓몬과 교체한다."
        ],
        "number": "017",
        "prodNumber": "019",
        "prodCode": "SVJP",
        "prodSymbolURL": "https://cards.image.pokemonkorea.co.kr/data/images/symbol/SVJP.png",
        "prodName": "스칼렛&바이올렛 배틀 마스터 덱 「파오젠 ex」",
        "artist": "NC Empire",
        "rarity": "N",
        "regulationMark": "G",
        "cardImgURL": "https://cards.image.pokemonkorea.co.kr/data/wmimages/SV/SVJP/SVJP_017.png?w=512",
        "cardPageURL": "https://pokemoncard.co.kr/cards/detail/BS2024010017"
    },
    {
        "id": "SVJP-018",
        "cardID": "주혜",
        "name": "주혜",
        "supertype": "트레이너스",
        "subtypes": [
            "서포트"
        ],
        "rules": [
            "서포트는 자신의 차례에 1장만 사용할 수 있다."
        ],
        "texts": [
            "자신의 덱에서 (물) 포켓몬과 아이템을 각각 1장씩 선택해서 상대에게 보여주고 패로 가져온다.",
            "그리고 덱을 섞는다."
        ],
        "number": "018",
        "prodNumber": "019",
        "prodCode": "SVJP",
        "prodSymbolURL": "https://cards.image.pokemonkorea.co.kr/data/images/symbol/SVJP.png",
        "prodName": "스칼렛&바이올렛 배틀 마스터 덱 「파오젠 ex」",
        "artist": "kirisAki",
        "rarity": "N",
        "regulationMark": "F",
        "cardImgURL": "https://cards.image.pokemonkorea.co.kr/data/wmimages/SV/SVJP/SVJP_018.png?w=512",
        "cardPageURL": "https://pokemoncard.co.kr/cards/detail/BS2024010018"
    },
    {
        "id": "SVJP-019",
        "cardID": "비치코트",
        "name": "비치코트",
        "supertype": "트레이너스",
        "subtypes": [
            "스타디움"
        ],
        "rules": [
            "스타디움은 자신의 차례에 1장 배틀필드 옆에 내놓을 수 있다.",
            "다른 스타디움이 필드에 나오면 이 카드를 트래쉬한다.",
            "같은 이름의 스타디움은 필드에 내보낼 수 없다."
        ],
        "texts": [
            "서로의 기본 포켓몬 전원의 후퇴에 필요한 에너지는 각각 1개만큼 적어진다."
        ],
        "number": "019",
        "prodNumber": "019",
        "prodCode": "SVJP",
        "prodSymbolURL": "https://cards.image.pokemonkorea.co.kr/data/images/symbol/SVJP.png",
        "prodName": "스칼렛&바이올렛 배틀 마스터 덱 「파오젠 ex」",
        "artist": "Oswaldo KATO",
        "rarity": "N",
        "regulationMark": "G",
        "cardImgURL": "https://cards.image.pokemonkorea.co.kr/data/wmimages/SV/SVJP/SVJP_019.png?w=512",
        "cardPageURL": "https://pokemoncard.co.kr/cards/detail/BS2024010019"
    },
    {
        "id": "SVJP-000",
        "cardID": "기본 물   에너지",
        "name": "기본 물   에너지",
        "supertype": "에너지",
        "subtypes": [
            "기본 에너지"
        ],
        "rules": [],
        "texts": [],
        "number": "000",
        "prodNumber": "WAT",
        "prodCode": "SVJP",
        "prodSymbolURL": "https://cards.image.pokemonkorea.co.kr/data/images/symbol/SVJP.png",
        "prodName": "스칼렛&바이올렛 배틀 마스터 덱 「파오젠 ex」",
        "rarity": "N",
        "regulationMark": "BE",
        "cardImgURL": "https://cards.image.pokemonkorea.co.kr/data/wmimages/SV/SVJP/SVJP_020.png?w=512",
        "cardPageURL": "https://pokemoncard.co.kr/cards/detail/BS2024010020"
    }
]