[
    {
        "id": "SA_R-000",
        "cardID": "기본 불꽃   에너지",
        "name": "기본 불꽃   에너지",
        "supertype": "에너지",
        "subtypes": [
            "기본 에너지"
        ],
        "rules": [],
        "texts": [],
        "number": "000",
        "prodNumber": "000",
        "prodCode": "SA_R",
        "prodSymbolURL": "https://cards.image.pokemonkorea.co.kr/data/images/symbol/SA_R.png",
        "prodName": "소드&실드 스타터 세트 V 불꽃",
        "rarity": "N",
        "regulationMark": "BE",
        "cardImgURL": "https://cards.image.pokemonkorea.co.kr/data/wmimages/S/SA/SA_R_Energy.png?w=512",
        "cardPageURL": "https://pokemoncard.co.kr/cards/detail/BS2020001048"
    },
    {
        "id": "SA_R-001",
        "cardID": "식스불070불꽃020",
        "name": "식스테일",
        "supertype": "포켓몬",
        "subtypes": [
            "기본"
        ],
        "rules": [],
        "hp": 70,
        "pokemons": [
            {
                "name": "식스테일",
                "pokedexNumber": 37
            }
        ],
        "type": "(불꽃)",
        "attacks": [
            {
                "name": "불꽃",
                "cost": "(불꽃)",
                "damage": "20",
                "text": ""
            }
        ],
        "abilities": [],
        "weakness": {
            "type": "(물)",
            "value": "×2"
        },
        "resistance": {
            "type": "",
            "value": "--"
        },
        "retreatCost": 1,
        "flavorText": "어리지만 6개의 꼬리가 아름답다. 성장하면 한층 꼬리 수가 늘어난다.",
        "number": "001",
        "prodNumber": "023",
        "prodCode": "SA_R",
        "prodSymbolURL": "https://cards.image.pokemonkorea.co.kr/data/images/symbol/SA_R.png",
        "prodName": "소드&실드 스타터 세트 V 불꽃",
        "artist": "Taira Akitsu",
        "rarity": "N",
        "regulationMark": "D",
        "cardImgURL": "https://cards.image.pokemonkorea.co.kr/data/wmimages/S/SA/SA_R_001.png?w=512",
        "cardPageURL": "https://pokemoncard.co.kr/cards/detail/BS2020001025"
    },
    {
        "id": "SA_R-002",
        "cardID": "나인불120불꽃030불꽃070",
        "name": "나인테일",
        "supertype": "포켓몬",
        "subtypes": [
            "1진화"
        ],
        "rules": [],
        "hp": 120,
        "pokemons": [
            {
                "name": "나인테일",
                "pokedexNumber": 38
            }
        ],
        "type": "(불꽃)",
        "attacks": [
            {
                "name": "불꽃두르기",
                "cost": "(불꽃)",
                "damage": "30",
                "text": "자신의 트래쉬에서 (불꽃) 에너지를 1장 선택해서 이 포켓몬에게 붙인다."
            },
            {
                "name": "불꽃의갈기",
                "cost": "(불꽃)(무색)",
                "damage": "70",
                "text": ""
            }
        ],
        "abilities": [],
        "weakness": {
            "type": "(물)",
            "value": "×2"
        },
        "resistance": {
            "type": "",
            "value": "--"
        },
        "retreatCost": 1,
        "flavorText": "꼬리 하나하나에 신통력이 담겨 있다. 1000년을 산다고 한다.",
        "number": "002",
        "prodNumber": "023",
        "prodCode": "SA_R",
        "prodSymbolURL": "https://cards.image.pokemonkorea.co.kr/data/images/symbol/SA_R.png",
        "prodName": "소드&실드 스타터 세트 V 불꽃",
        "artist": "Megumi Higuchi",
        "rarity": "N",
        "regulationMark": "D",
        "cardImgURL": "https://cards.image.pokemonkorea.co.kr/data/wmimages/S/SA/SA_R_002.png?w=512",
        "cardPageURL": "https://pokemoncard.co.kr/cards/detail/BS2020001026"
    },
    {
        "id": "SA_R-003",
        "cardID": "비크불190퍼지000에너030",
        "name": "비크티니 V",
        "supertype": "포켓몬",
        "subtypes": [
            "기본",
            "V"
        ],
        "rules": [
            "포켓몬 V가 기절한 경우 상대는 프라이즈를 2장 가져간다."
        ],
        "hp": 190,
        "pokemons": [
            {
                "name": "비크티니",
                "pokedexNumber": 494
            }
        ],
        "type": "(불꽃)",
        "attacks": [
            {
                "name": "퍼지는불꽃",
                "cost": "(무색)",
                "damage": "",
                "text": "자신의 트래쉬에서 (불꽃) 에너지를 3장까지 선택해서 자신의 포켓몬에게 원하는 대로 붙인다."
            },
            {
                "name": "에너지버스트",
                "cost": "(불꽃)(불꽃)",
                "damage": "30×",
                "text": "서로의 배틀 포켓몬에게 붙어 있는 에너지의 개수 × 30데미지를 준다."
            }
        ],
        "abilities": [],
        "weakness": {
            "type": "(물)",
            "value": "×2"
        },
        "resistance": {
            "type": "",
            "value": "--"
        },
        "retreatCost": 2,
        "flavorText": "",
        "number": "003",
        "prodNumber": "023",
        "prodCode": "SA_R",
        "prodSymbolURL": "https://cards.image.pokemonkorea.co.kr/data/images/symbol/SA_R.png",
        "prodName": "소드&실드 스타터 세트 V 불꽃",
        "artist": "PLANETA Tsuji",
        "rarity": "N",
        "regulationMark": "D",
        "cardImgURL": "https://cards.image.pokemonkorea.co.kr/data/wmimages/S/SA/SA_R_003.png?w=512",
        "cardPageURL": "https://pokemoncard.co.kr/cards/detail/BS2020001027"
    },
    {
        "id": "SA_R-004",
        "cardID": "앤티불110태워010불꽃050",
        "name": "앤티골",
        "supertype": "포켓몬",
        "subtypes": [
            "기본"
        ],
        "rules": [],
        "hp": 110,
        "pokemons": [
            {
                "name": "앤티골",
                "pokedexNumber": 631
            }
        ],
        "type": "(불꽃)",
        "attacks": [
            {
                "name": "태워그을리기",
                "cost": "(불꽃)",
                "damage": "10",
                "text": "상대의 배틀 포켓몬을 화상으로 만든다."
            },
            {
                "name": "불꽃의발톱",
                "cost": "(불꽃)(불꽃)",
                "damage": "50",
                "text": ""
            }
        ],
        "abilities": [],
        "weakness": {
            "type": "(물)",
            "value": "×2"
        },
        "resistance": {
            "type": "",
            "value": "--"
        },
        "retreatCost": 1,
        "flavorText": "꼬리의 구멍을 통해 공기를 빨아들여 불꽃을 태운다. 구멍이 막히면 상태가 나빠진다.",
        "number": "004",
        "prodNumber": "023",
        "prodCode": "SA_R",
        "prodSymbolURL": "https://cards.image.pokemonkorea.co.kr/data/images/symbol/SA_R.png",
        "prodName": "소드&실드 스타터 세트 V 불꽃",
        "artist": "kawayoo",
        "rarity": "N",
        "regulationMark": "D",
        "cardImgURL": "https://cards.image.pokemonkorea.co.kr/data/wmimages/S/SA/SA_R_004.png?w=512",
        "cardPageURL": "https://pokemoncard.co.kr/cards/detail/BS2020001028"
    },
    {
        "id": "SA_R-005",
        "cardID": "폭거불130몸통030회오150",
        "name": "폭거북스",
        "supertype": "포켓몬",
        "subtypes": [
            "기본"
        ],
        "rules": [],
        "hp": 130,
        "pokemons": [
            {
                "name": "폭거북스",
                "pokedexNumber": 776
            }
        ],
        "type": "(불꽃)",
        "attacks": [
            {
                "name": "몸통박치기",
                "cost": "(무색)(무색)",
                "damage": "30",
                "text": ""
            },
            {
                "name": "회오리불꽃",
                "cost": "(불꽃)(불꽃)(불꽃)(무색)",
                "damage": "150",
                "text": "이 포켓몬에게 붙어 있는 에너지를 2개 선택해서 트래쉬한다."
            }
        ],
        "abilities": [],
        "weakness": {
            "type": "(물)",
            "value": "×2"
        },
        "resistance": {
            "type": "",
            "value": "--"
        },
        "retreatCost": 3,
        "flavorText": "폭약으로 코팅된 등껍질을 짊어지고 있다. 공격하는 상대에게 대폭발로 반격한다.",
        "number": "005",
        "prodNumber": "023",
        "prodCode": "SA_R",
        "prodSymbolURL": "https://cards.image.pokemonkorea.co.kr/data/images/symbol/SA_R.png",
        "prodName": "소드&실드 스타터 세트 V 불꽃",
        "artist": "KEIICHIRO ITO",
        "rarity": "N",
        "regulationMark": "D",
        "cardImgURL": "https://cards.image.pokemonkorea.co.kr/data/wmimages/S/SA/SA_R_005.png?w=512",
        "cardPageURL": "https://pokemoncard.co.kr/cards/detail/BS2020001029"
    },
    {
        "id": "SA_R-006",
        "cardID": "염버불070몸통010불꽃020",
        "name": "염버니",
        "supertype": "포켓몬",
        "subtypes": [
            "기본"
        ],
        "rules": [],
        "hp": 70,
        "pokemons": [
            {
                "name": "염버니",
                "pokedexNumber": 813
            }
        ],
        "type": "(불꽃)",
        "attacks": [
            {
                "name": "몸통박치기",
                "cost": "(무색)",
                "damage": "10",
                "text": ""
            },
            {
                "name": "불꽃",
                "cost": "(불꽃)(무색)",
                "damage": "20",
                "text": ""
            }
        ],
        "abilities": [],
        "weakness": {
            "type": "(물)",
            "value": "×2"
        },
        "resistance": {
            "type": "",
            "value": "--"
        },
        "retreatCost": 1,
        "flavorText": "뛰어다니며 체온을 높이면 불꽃 에너지가 몸 안에 맴돌아 본래의 힘을 발휘할 수 있다.",
        "number": "006",
        "prodNumber": "023",
        "prodCode": "SA_R",
        "prodSymbolURL": "https://cards.image.pokemonkorea.co.kr/data/images/symbol/SA_R.png",
        "prodName": "소드&실드 스타터 세트 V 불꽃",
        "artist": "Kagemaru Himeno",
        "rarity": "N",
        "regulationMark": "D",
        "cardImgURL": "https://cards.image.pokemonkorea.co.kr/data/wmimages/S/SA/SA_R_006.png?w=512",
        "cardPageURL": "https://pokemoncard.co.kr/cards/detail/BS2020001030"
    },
    {
        "id": "SA_R-007",
        "cardID": "래비불090킥킥020히트050",
        "name": "래비풋",
        "supertype": "포켓몬",
        "subtypes": [
            "1진화"
        ],
        "rules": [],
        "hp": 90,
        "pokemons": [
            {
                "name": "래비풋",
                "pokedexNumber": 814
            }
        ],
        "type": "(불꽃)",
        "attacks": [
            {
                "name": "킥",
                "cost": "(무색)",
                "damage": "20",
                "text": ""
            },
            {
                "name": "히트블라스트",
                "cost": "(불꽃)(불꽃)",
                "damage": "50",
                "text": ""
            }
        ],
        "abilities": [],
        "weakness": {
            "type": "(물)",
            "value": "×2"
        },
        "resistance": {
            "type": "",
            "value": "--"
        },
        "retreatCost": 1,
        "flavorText": "푹신푹신한 털 덕분에 추위에 강해지고 더 높은 온도의 불꽃 기술도 쓸 수 있게 되었다.",
        "number": "007",
        "prodNumber": "023",
        "prodCode": "SA_R",
        "prodSymbolURL": "https://cards.image.pokemonkorea.co.kr/data/images/symbol/SA_R.png",
        "prodName": "소드&실드 스타터 세트 V 불꽃",
        "artist": "Akira Komayama",
        "rarity": "N",
        "regulationMark": "D",
        "cardImgURL": "https://cards.image.pokemonkorea.co.kr/data/wmimages/S/SA/SA_R_007.png?w=512",
        "cardPageURL": "https://pokemoncard.co.kr/cards/detail/BS2020001031"
    },
    {
        "id": "SA_R-008",
        "cardID": "에이불170화염050버닝160",
        "name": "에이스번",
        "supertype": "포켓몬",
        "subtypes": [
            "2진화"
        ],
        "rules": [],
        "hp": 170,
        "pokemons": [
            {
                "name": "에이스번",
                "pokedexNumber": 815
            }
        ],
        "type": "(불꽃)",
        "attacks": [
            {
                "name": "화염볼",
                "cost": "(불꽃)",
                "damage": "50",
                "text": "상대의 배틀 포켓몬을 화상으로 만든다."
            },
            {
                "name": "버닝킥",
                "cost": "(불꽃)(불꽃)",
                "damage": "160",
                "text": "이 포켓몬에게 붙어 있는 에너지를 모두 트래쉬한다."
            }
        ],
        "abilities": [],
        "weakness": {
            "type": "(물)",
            "value": "×2"
        },
        "resistance": {
            "type": "",
            "value": "--"
        },
        "retreatCost": 1,
        "flavorText": "작은 돌을 리프팅해서 불꽃의 축구공을 만들고 날카로운 슛으로 상대를 태워버린다.",
        "number": "008",
        "prodNumber": "023",
        "prodCode": "SA_R",
        "prodSymbolURL": "https://cards.image.pokemonkorea.co.kr/data/images/symbol/SA_R.png",
        "prodName": "소드&실드 스타터 세트 V 불꽃",
        "artist": "Naoki Saito",
        "rarity": "N",
        "regulationMark": "D",
        "cardImgURL": "https://cards.image.pokemonkorea.co.kr/data/wmimages/S/SA/SA_R_008.png?w=512",
        "cardPageURL": "https://pokemoncard.co.kr/cards/detail/BS2020001032"
    },
    {
        "id": "SA_R-009",
        "cardID": "태우불070연속040",
        "name": "태우지네",
        "supertype": "포켓몬",
        "subtypes": [
            "기본"
        ],
        "rules": [],
        "hp": 70,
        "pokemons": [
            {
                "name": "태우지네",
                "pokedexNumber": 850
            }
        ],
        "type": "(불꽃)",
        "attacks": [
            {
                "name": "연속파이어",
                "cost": "(불꽃)(무색)",
                "damage": "40×",
                "text": "뒷면이 나올 때까지 동전을 던져서 앞면이 나온 수 × 40데미지를 준다."
            }
        ],
        "abilities": [],
        "weakness": {
            "type": "(물)",
            "value": "×2"
        },
        "resistance": {
            "type": "",
            "value": "--"
        },
        "retreatCost": 1,
        "flavorText": "몸속에 모아둔 가연성 가스로 열을 낸다. 특히 배 쪽의 노란 부분이 뜨겁다.",
        "number": "009",
        "prodNumber": "023",
        "prodCode": "SA_R",
        "prodSymbolURL": "https://cards.image.pokemonkorea.co.kr/data/images/symbol/SA_R.png",
        "prodName": "소드&실드 스타터 세트 V 불꽃",
        "artist": "Kouki Saitou",
        "rarity": "N",
        "regulationMark": "D",
        "cardImgURL": "https://cards.image.pokemonkorea.co.kr/data/wmimages/S/SA/SA_R_009.png?w=512",
        "cardPageURL": "https://pokemoncard.co.kr/cards/detail/BS2020001033"
    },
    {
        "id": "SA_R-010",
        "cardID": "치라무060꼬리030",
        "name": "치라미",
        "supertype": "포켓몬",
        "subtypes": [
            "기본"
        ],
        "rules": [],
        "hp": 60,
        "pokemons": [
            {
                "name": "치라미",
                "pokedexNumber": 572
            }
        ],
        "type": "(무색)",
        "attacks": [
            {
                "name": "꼬리로 막치기",
                "cost": "(무색)",
                "damage": "30",
                "text": ""
            }
        ],
        "abilities": [],
        "weakness": {
            "type": "(격투)",
            "value": "×2"
        },
        "resistance": {
            "type": "",
            "value": "--"
        },
        "retreatCost": 1,
        "flavorText": "꼬리로 더러운 것을 떨어낸다. 청소를 할 때는 도움이 되지만 결벽증이 있어서 힘들기도 하다.",
        "number": "010",
        "prodNumber": "023",
        "prodCode": "SA_R",
        "prodSymbolURL": "https://cards.image.pokemonkorea.co.kr/data/images/symbol/SA_R.png",
        "prodName": "소드&실드 스타터 세트 V 불꽃",
        "artist": "sowsow",
        "rarity": "N",
        "regulationMark": "D",
        "cardImgURL": "https://cards.image.pokemonkorea.co.kr/data/wmimages/S/SA/SA_R_010.png?w=512",
        "cardPageURL": "https://pokemoncard.co.kr/cards/detail/BS2020001034"
    },
    {
        "id": "SA_R-011",
        "cardID": "수퍼볼",
        "name": "수퍼볼",
        "supertype": "트레이너스",
        "subtypes": [
            "아이템"
        ],
        "rules": [
            "아이템은 자신의 차례에 몇 장이라도 사용할 수 있다."
        ],
        "texts": [
            "자신의 덱을 위에서부터 7장 본다.",
            "그 중에서 포켓몬을 1장 선택해서 상대에게 보여주고 패로 가져온다.",
            "남은 카드는 덱으로 되돌리고 섞는다."
        ],
        "number": "011",
        "prodNumber": "023",
        "prodCode": "SA_R",
        "prodSymbolURL": "https://cards.image.pokemonkorea.co.kr/data/images/symbol/SA_R.png",
        "prodName": "소드&실드 스타터 세트 V 불꽃",
        "artist": "Toyste Beach",
        "rarity": "N",
        "regulationMark": "D",
        "cardImgURL": "https://cards.image.pokemonkorea.co.kr/data/wmimages/S/SA/SA_R_011.png?w=512",
        "cardPageURL": "https://pokemoncard.co.kr/cards/detail/BS2020001035"
    },
    {
        "id": "SA_R-012",
        "cardID": "에너지 전송",
        "name": "에너지 전송",
        "supertype": "트레이너스",
        "subtypes": [
            "아이템"
        ],
        "rules": [
            "아이템은 자신의 차례에 몇 장이라도 사용할 수 있다."
        ],
        "texts": [
            "자신의 덱에서 기본 에너지를 1장 선택해서 상대에게 보여주고 패로 가져온다.",
            "그리고 덱을 섞는다."
        ],
        "number": "012",
        "prodNumber": "023",
        "prodCode": "SA_R",
        "prodSymbolURL": "https://cards.image.pokemonkorea.co.kr/data/images/symbol/SA_R.png",
        "prodName": "소드&실드 스타터 세트 V 불꽃",
        "artist": "Studio Bora Inc.",
        "rarity": "N",
        "regulationMark": "D",
        "cardImgURL": "https://cards.image.pokemonkorea.co.kr/data/wmimages/S/SA/SA_R_012.png?w=512",
        "cardPageURL": "https://pokemoncard.co.kr/cards/detail/BS2020001036"
    },
    {
        "id": "SA_R-013",
        "cardID": "이상한사탕",
        "name": "이상한사탕",
        "supertype": "트레이너스",
        "subtypes": [
            "아이템"
        ],
        "rules": [
            "아이템은 자신의 차례에 몇 장이라도 사용할 수 있다."
        ],
        "texts": [
            "자신의 패에서 2진화 포켓몬을 1장 선택해서 그 포켓몬으로 진화하는 자신의 필드의 기본 포켓몬 위에 올려 1진화를 건너뛰어 진화시킨다.",
            "(자신의 첫 번째 차례와 이번 차례에 내보낸 포켓몬에게는 사용할 수 없다.)"
        ],
        "number": "013",
        "prodNumber": "023",
        "prodCode": "SA_R",
        "prodSymbolURL": "https://cards.image.pokemonkorea.co.kr/data/images/symbol/SA_R.png",
        "prodName": "소드&실드 스타터 세트 V 불꽃",
        "artist": "Yoshinobu Saito",
        "rarity": "N",
        "regulationMark": "D",
        "cardImgURL": "https://cards.image.pokemonkorea.co.kr/data/wmimages/S/SA/SA_R_013.png?w=512",
        "cardPageURL": "https://pokemoncard.co.kr/cards/detail/BS2020001037"
    },
    {
        "id": "SA_R-014",
        "cardID": "진화향로",
        "name": "진화향로",
        "supertype": "트레이너스",
        "subtypes": [
            "아이템"
        ],
        "rules": [
            "아이템은 자신의 차례에 몇 장이라도 사용할 수 있다."
        ],
        "texts": [
            "자신의 덱에서 진화 포켓몬을 1장 선택해서 상대에게 보여주고 패로 가져온다.",
            "그리고 덱을 섞는다."
        ],
        "number": "014",
        "prodNumber": "023",
        "prodCode": "SA_R",
        "prodSymbolURL": "https://cards.image.pokemonkorea.co.kr/data/images/symbol/SA_R.png",
        "prodName": "소드&실드 스타터 세트 V 불꽃",
        "artist": "Ryo Ueda",
        "rarity": "N",
        "regulationMark": "D",
        "cardImgURL": "https://cards.image.pokemonkorea.co.kr/data/wmimages/S/SA/SA_R_014.png?w=512",
        "cardPageURL": "https://pokemoncard.co.kr/cards/detail/BS2020001038"
    },
    {
        "id": "SA_R-015",
        "cardID": "크래시 해머",
        "name": "크래시 해머",
        "supertype": "트레이너스",
        "subtypes": [
            "아이템"
        ],
        "rules": [
            "아이템은 자신의 차례에 몇 장이라도 사용할 수 있다."
        ],
        "texts": [
            "동전을 1번 던져서 앞면이 나오면 상대 필드의 포켓몬에게 붙어 있는 에너지를 1개 선택해서 트래쉬한다."
        ],
        "number": "015",
        "prodNumber": "023",
        "prodCode": "SA_R",
        "prodSymbolURL": "https://cards.image.pokemonkorea.co.kr/data/images/symbol/SA_R.png",
        "prodName": "소드&실드 스타터 세트 V 불꽃",
        "artist": "sadaji",
        "rarity": "N",
        "regulationMark": "D",
        "cardImgURL": "https://cards.image.pokemonkorea.co.kr/data/wmimages/S/SA/SA_R_015.png?w=512",
        "cardPageURL": "https://pokemoncard.co.kr/cards/detail/BS2020001039"
    },
    {
        "id": "SA_R-016",
        "cardID": "포켓기어3.0",
        "name": "포켓기어3.0",
        "supertype": "트레이너스",
        "subtypes": [
            "아이템"
        ],
        "rules": [
            "아이템은 자신의 차례에 몇 장이라도 사용할 수 있다."
        ],
        "texts": [
            "자신의 덱을 위에서부터 7장 본다.",
            "그 중에서 서포트를 1장 선택해서 상대에게 보여주고 패로 가져온다.",
            "남은 카드는 덱으로 되돌리고 섞는다."
        ],
        "number": "016",
        "prodNumber": "023",
        "prodCode": "SA_R",
        "prodSymbolURL": "https://cards.image.pokemonkorea.co.kr/data/images/symbol/SA_R.png",
        "prodName": "소드&실드 스타터 세트 V 불꽃",
        "artist": "Ryo Ueda",
        "rarity": "N",
        "regulationMark": "D",
        "cardImgURL": "https://cards.image.pokemonkorea.co.kr/data/wmimages/S/SA/SA_R_016.png?w=512",
        "cardPageURL": "https://pokemoncard.co.kr/cards/detail/BS2020001040"
    },
    {
        "id": "SA_R-017",
        "cardID": "포켓몬 교체",
        "name": "포켓몬 교체",
        "supertype": "트레이너스",
        "subtypes": [
            "아이템"
        ],
        "rules": [
            "아이템은 자신의 차례에 몇 장이라도 사용할 수 있다."
        ],
        "texts": [
            "자신의 배틀 포켓몬을 벤치 포켓몬과 교체한다."
        ],
        "number": "017",
        "prodNumber": "023",
        "prodCode": "SA_R",
        "prodSymbolURL": "https://cards.image.pokemonkorea.co.kr/data/images/symbol/SA_R.png",
        "prodName": "소드&실드 스타터 세트 V 불꽃",
        "artist": "Studio Bora Inc.",
        "rarity": "N",
        "regulationMark": "D",
        "cardImgURL": "https://cards.image.pokemonkorea.co.kr/data/wmimages/S/SA/SA_R_017.png?w=512",
        "cardPageURL": "https://pokemoncard.co.kr/cards/detail/BS2020001041"
    },
    {
        "id": "SA_R-018",
        "cardID": "포켓몬 캐처",
        "name": "포켓몬 캐처",
        "supertype": "트레이너스",
        "subtypes": [
            "아이템"
        ],
        "rules": [
            "아이템은 자신의 차례에 몇 장이라도 사용할 수 있다."
        ],
        "texts": [
            "동전을 1번 던져서 앞면이 나오면 상대의 벤치 포켓몬을 1마리 선택해서 배틀 포켓몬과 교체한다."
        ],
        "number": "018",
        "prodNumber": "023",
        "prodCode": "SA_R",
        "prodSymbolURL": "https://cards.image.pokemonkorea.co.kr/data/images/symbol/SA_R.png",
        "prodName": "소드&실드 스타터 세트 V 불꽃",
        "artist": "Ryo Ueda",
        "rarity": "N",
        "regulationMark": "D",
        "cardImgURL": "https://cards.image.pokemonkorea.co.kr/data/wmimages/S/SA/SA_R_018.png?w=512",
        "cardPageURL": "https://pokemoncard.co.kr/cards/detail/BS2020001042"
    },
    {
        "id": "SA_R-019",
        "cardID": "기력의머리띠",
        "name": "기력의머리띠",
        "supertype": "트레이너스",
        "subtypes": [
            "포켓몬의 도구"
        ],
        "rules": [
            "포켓몬의 도구는 자신의 포켓몬에게 붙여서 사용한다.",
            "포켓몬 1마리에게 1장만 붙일 수 있고 붙인 채로 둔다.",
            "아이템은 자신의 차례에 몇 장이라도 사용할 수 있다."
        ],
        "texts": [
            "이 카드를 붙이고 있는 포켓몬이 사용하는 기술이 상대의 배틀 포켓몬에게 주는 데미지는 「+10」이 된다."
        ],
        "number": "019",
        "prodNumber": "023",
        "prodCode": "SA_R",
        "prodSymbolURL": "https://cards.image.pokemonkorea.co.kr/data/images/symbol/SA_R.png",
        "prodName": "소드&실드 스타터 세트 V 불꽃",
        "artist": "Toyste Beach",
        "rarity": "N",
        "regulationMark": "D",
        "cardImgURL": "https://cards.image.pokemonkorea.co.kr/data/wmimages/S/SA/SA_R_019.png?w=512",
        "cardPageURL": "https://pokemoncard.co.kr/cards/detail/BS2020001043"
    },
    {
        "id": "SA_R-020",
        "cardID": "마리",
        "name": "마리",
        "supertype": "트레이너스",
        "subtypes": [
            "서포트"
        ],
        "rules": [
            "서포트는 자신의 차례에 1장만 사용할 수 있다."
        ],
        "texts": [
            "서로의 플레이어는 각각 자신의 패를 모두 뒷면으로 하여 섞고 덱의 아래로 되돌린다.",
            "자신은 5장 상대는 4장 덱을 뽑는다."
        ],
        "number": "020",
        "prodNumber": "023",
        "prodCode": "SA_R",
        "prodSymbolURL": "https://cards.image.pokemonkorea.co.kr/data/images/symbol/SA_R.png",
        "prodName": "소드&실드 스타터 세트 V 불꽃",
        "artist": "kirisAki",
        "rarity": "N",
        "regulationMark": "D",
        "cardImgURL": "https://cards.image.pokemonkorea.co.kr/data/wmimages/S/SA/SA_R_020.png?w=512",
        "cardPageURL": "https://pokemoncard.co.kr/cards/detail/BS2020001044"
    },
    {
        "id": "SA_R-021",
        "cardID": "박사의 연구(매그놀리아박사)",
        "name": "박사의 연구(매그놀리아박사)",
        "supertype": "트레이너스",
        "subtypes": [
            "서포트"
        ],
        "rules": [
            "서포트는 자신의 차례에 1장만 사용할 수 있다."
        ],
        "texts": [
            "자신의 패를 모두 트래쉬하고 덱을 7장 뽑는다."
        ],
        "number": "021",
        "prodNumber": "023",
        "prodCode": "SA_R",
        "prodSymbolURL": "https://cards.image.pokemonkorea.co.kr/data/images/symbol/SA_R.png",
        "prodName": "소드&실드 스타터 세트 V 불꽃",
        "artist": "Yusuke Ohmura",
        "rarity": "N",
        "regulationMark": "D",
        "cardImgURL": "https://cards.image.pokemonkorea.co.kr/data/wmimages/S/SA/SA_R_021.png?w=512",
        "cardPageURL": "https://pokemoncard.co.kr/cards/detail/BS2020001045"
    },
    {
        "id": "SA_R-022",
        "cardID": "포켓몬놀이",
        "name": "포켓몬놀이",
        "supertype": "트레이너스",
        "subtypes": [
            "서포트"
        ],
        "rules": [
            "서포트는 자신의 차례에 1장만 사용할 수 있다."
        ],
        "texts": [
            "자신의 덱에서 포켓몬을 1장 선택해서 상대에게 보여주고 패로 가져온다.",
            "그리고 덱을 섞는다."
        ],
        "number": "022",
        "prodNumber": "023",
        "prodCode": "SA_R",
        "prodSymbolURL": "https://cards.image.pokemonkorea.co.kr/data/images/symbol/SA_R.png",
        "prodName": "소드&실드 스타터 세트 V 불꽃",
        "artist": "Hitoshi Ariga",
        "rarity": "N",
        "regulationMark": "D",
        "cardImgURL": "https://cards.image.pokemonkorea.co.kr/data/wmimages/S/SA/SA_R_022.png?w=512",
        "cardPageURL": "https://pokemoncard.co.kr/cards/detail/BS2020001046"
    },
    {
        "id": "SA_R-023",
        "cardID": "호브",
        "name": "호브",
        "supertype": "트레이너스",
        "subtypes": [
            "서포트"
        ],
        "rules": [
            "서포트는 자신의 차례에 1장만 사용할 수 있다."
        ],
        "texts": [
            "자신의 덱을 3장 뽑는다."
        ],
        "number": "023",
        "prodNumber": "023",
        "prodCode": "SA_R",
        "prodSymbolURL": "https://cards.image.pokemonkorea.co.kr/data/images/symbol/SA_R.png",
        "prodName": "소드&실드 스타터 세트 V 불꽃",
        "artist": "Ken Sugimori",
        "rarity": "N",
        "regulationMark": "D",
        "cardImgURL": "https://cards.image.pokemonkorea.co.kr/data/wmimages/S/SA/SA_R_023.png?w=512",
        "cardPageURL": "https://pokemoncard.co.kr/cards/detail/BS2020001047"
    }
]