[
    {
        "id": "bd-007",
        "cardID": "페라무070음치010쪼기030",
        "name": "페라페",
        "supertype": "포켓몬",
        "subtypes": [
            "기본"
        ],
        "rules": [],
        "hp": 70,
        "pokemons": [
            {
                "name": "페라페",
                "pokedexNumber": 441
            }
        ],
        "type": "(무색)",
        "attacks": [
            {
                "name": "음치",
                "cost": "(무색)",
                "damage": "10",
                "text": "동전을 한 번 던져서 앞면이 나오면 상대의 배틀 포켓몬을 혼란으로 만든다."
            },
            {
                "name": "쪼기",
                "cost": "(무색)(무색)",
                "damage": "30",
                "text": ""
            }
        ],
        "abilities": [],
        "weakness": {
            "type": "(번개)",
            "value": "×2"
        },
        "resistance": {
            "type": "(격투)",
            "value": "-20"
        },
        "retreatCost": 1,
        "flavorText": "혀는 인간의 것을 똑 닮았다. 그 때문에 인간이 하는 말을 능숙하게 흉내 낼 수 있다.",
        "regulationMark": [
            "BW"
        ],
        "version_infos": [
            {
                "number": "007",
                "prodNumber": "013",
                "prodCode": "bd",
                "prodSymbolURL": "https://cards.image.pokemonkorea.co.kr/data/images/symbol/bd.png",
                "prodName": "BW 「볼트로스 덱」",
                "artist": "MAHOU",
                "rarity": "N",
                "cardImgURL": "https://cards.image.pokemonkorea.co.kr/data/wmimages/BW/BD/bw_bd_007.jpg?w=512",
                "cardPageURL": "https://pokemoncard.co.kr/cards/detail/ST2012004007",
                "debug": "1"
            }
        ]
    },
    {
        "id": "bw9-064",
        "cardID": "페라무060거짓000음치020",
        "name": "페라페",
        "supertype": "포켓몬",
        "subtypes": [
            "기본",
            "플라스마단"
        ],
        "rules": [],
        "hp": 60,
        "pokemons": [
            {
                "name": "페라페",
                "pokedexNumber": 441
            }
        ],
        "type": "(무색)",
        "attacks": [
            {
                "name": "거짓정보",
                "cost": "(무색)",
                "damage": "",
                "text": "상대의 포켓몬 전원에게 붙어 있는 「포켓몬의 도구」를 모두 트래쉬한다."
            },
            {
                "name": "음치",
                "cost": "(무색)(무색)",
                "damage": "20",
                "text": "상대의 배틀 포켓몬을 혼란으로 만든다."
            }
        ],
        "abilities": [],
        "weakness": {
            "type": "(번개)",
            "value": "×2"
        },
        "resistance": {
            "type": "(격투)",
            "value": "-20"
        },
        "retreatCost": 1,
        "flavorText": "혀는 인간의 것을 똑 닮았다. 그 때문에 인간이 하는 말을 능숙하게 흉내 낼 수 있다.",
        "regulationMark": [
            "BW"
        ],
        "version_infos": [
            {
                "number": "064",
                "prodNumber": "076",
                "prodCode": "bw9",
                "prodSymbolURL": "https://cards.image.pokemonkorea.co.kr/data/images/symbol/bw9.png",
                "prodName": "BW 확장팩 제9탄 「메갈로캐논」",
                "artist": "5ban Graphics",
                "rarity": "C",
                "cardImgURL": "https://cards.image.pokemonkorea.co.kr/data/wmimages/BW/BW9/bw9_064.jpg?w=512",
                "cardPageURL": "https://pokemoncard.co.kr/cards/detail/BS2013005064",
                "debug": "1"
            }
        ]
    },
    {
        "id": "ubd-006",
        "cardID": "페라무070노래000제비010",
        "name": "페라페",
        "supertype": "포켓몬",
        "subtypes": [
            "기본"
        ],
        "rules": [],
        "hp": 70,
        "pokemons": [
            {
                "name": "페라페",
                "pokedexNumber": 441
            }
        ],
        "type": "(무색)",
        "attacks": [
            {
                "name": "노래하기",
                "cost": "(무색)",
                "damage": "",
                "text": "상대의 배틀 포켓몬을 잠듦으로 만든다."
            },
            {
                "name": "제비반환",
                "cost": "(무색)(무색)",
                "damage": "10+",
                "text": "동전을 한 번 던져서 앞면이 나오면 30데미지를 추가한다."
            }
        ],
        "abilities": [],
        "weakness": {
            "type": "(번개)",
            "value": "×2"
        },
        "resistance": {
            "type": "(격투)",
            "value": "-20"
        },
        "retreatCost": 1,
        "flavorText": "사람의 말을 기억해서 운다. 동료가 한 장소에 모이면 모두 똑같은 말을 기억한다.",
        "regulationMark": [
            "XY"
        ],
        "version_infos": [
            {
                "number": "006",
                "prodNumber": "017",
                "prodCode": "ubd",
                "prodSymbolURL": "https://cards.image.pokemonkorea.co.kr/data/images/symbol/ubd.png",
                "prodName": "XY BREAK 30장 덱 「음번 BREAK」",
                "artist": "Akira Komayama",
                "rarity": "N",
                "cardImgURL": "https://cards.image.pokemonkorea.co.kr/data/wmimages/XY/UBD/UBD_006.jpg?w=512",
                "cardPageURL": "https://pokemoncard.co.kr/cards/detail/ST2015005006",
                "debug": "3"
            }
        ]
    },
    {
        "id": "sm10-078",
        "cardID": "페라무070흉내000음치010",
        "name": "페라페",
        "supertype": "포켓몬",
        "subtypes": [
            "기본"
        ],
        "rules": [],
        "hp": 70,
        "pokemons": [
            {
                "name": "페라페",
                "pokedexNumber": 441
            }
        ],
        "type": "(무색)",
        "attacks": [
            {
                "name": "흉내내기",
                "cost": "(무색)",
                "damage": "",
                "text": "자신의 패를 모두 덱으로 되돌리고 섞는다. 그 뒤, 상대의 패의 장수만큼 자신의 덱을 뽑는다."
            },
            {
                "name": "음치",
                "cost": "(무색)",
                "damage": "10",
                "text": "상대의 배틀 포켓몬을 혼란으로 만든다."
            }
        ],
        "abilities": [],
        "weakness": {
            "type": "(번개)",
            "value": "×2"
        },
        "resistance": {
            "type": "(격투)",
            "value": "-20"
        },
        "retreatCost": 1,
        "flavorText": "상대와 같은 울음소리를 내서 동료라고 굳게 믿게 하여 습격당하지 않도록 하고 있다.",
        "regulationMark": [
            "C"
        ],
        "version_infos": [
            {
                "number": "078",
                "prodNumber": "095",
                "prodCode": "sm10",
                "prodSymbolURL": "https://cards.image.pokemonkorea.co.kr/data/images/symbol/sm10.png",
                "prodName": "썬&문 확장팩 「더블블레이즈」",
                "artist": "HYOGONOSUKE",
                "rarity": "C",
                "cardImgURL": "https://cards.image.pokemonkorea.co.kr/data/wmimages/SM/SM10/SM10_078.png?w=512",
                "cardPageURL": "https://pokemoncard.co.kr/cards/detail/BS2019007078",
                "debug": "1"
            }
        ]
    },
    {
        "id": "S2-078",
        "cardID": "페라무070럭키활공030",
        "name": "페라페",
        "supertype": "포켓몬",
        "subtypes": [
            "기본"
        ],
        "rules": [],
        "hp": 70,
        "pokemons": [
            {
                "name": "페라페",
                "pokedexNumber": 441
            }
        ],
        "type": "(무색)",
        "attacks": [
            {
                "name": "활공",
                "cost": "(무색)(무색)",
                "damage": "30",
                "text": ""
            }
        ],
        "abilities": [
            {
                "name": "럭키매치",
                "text": "자신의 차례에 이 카드를 패에서 벤치로 내보냈을 때 1번 사용할 수 있다. 동전을 1번 던져서 앞면이 나오면 자신의 트래쉬에서 서포트를 1장 선택해서 상대에게 보여주고 패로 가져온다.",
                "type": "특성"
            }
        ],
        "weakness": {
            "type": "(번개)",
            "value": "×2"
        },
        "resistance": {
            "type": "(격투)",
            "value": "-30"
        },
        "retreatCost": 1,
        "flavorText": "사람의 말을 기억해서 운다. 동료가 한 장소에 모이면 모두 똑같은 말을 기억한다.",
        "regulationMark": [
            "D"
        ],
        "version_infos": [
            {
                "number": "078",
                "prodNumber": "096",
                "prodCode": "S2",
                "prodSymbolURL": "https://cards.image.pokemonkorea.co.kr/data/images/symbol/S2.png",
                "prodName": "소드&실드 확장팩 「반역크래시」",
                "artist": "ryoma uratsuka",
                "rarity": "C",
                "cardImgURL": "https://cards.image.pokemonkorea.co.kr/data/wmimages/S/S2/S2_078.png?w=512",
                "cardPageURL": "https://pokemoncard.co.kr/cards/detail/BS2020005078",
                "debug": "1"
            }
        ]
    },
    {
        "id": "S3a-057",
        "cardID": "페라무070작은000쪼기020",
        "name": "페라페",
        "supertype": "포켓몬",
        "subtypes": [
            "기본"
        ],
        "rules": [],
        "hp": 70,
        "pokemons": [
            {
                "name": "페라페",
                "pokedexNumber": 441
            }
        ],
        "type": "(무색)",
        "attacks": [
            {
                "name": "작은 선물",
                "cost": "(무색)",
                "damage": "",
                "text": "자신의 덱에서 기본 에너지를 2장까지 선택해서 상대에게 보여주고 패로 가져온다. 그리고 덱을 섞는다."
            },
            {
                "name": "쪼기",
                "cost": "(무색)",
                "damage": "20",
                "text": ""
            }
        ],
        "abilities": [],
        "weakness": {
            "type": "(번개)",
            "value": "×2"
        },
        "resistance": {
            "type": "(격투)",
            "value": "-30"
        },
        "retreatCost": 1,
        "flavorText": "사람의 말을 기억해서 운다. 동료가 한 장소에 모이면 모두 똑같은 말을 기억한다.",
        "regulationMark": [
            "D"
        ],
        "version_infos": [
            {
                "number": "057",
                "prodNumber": "076",
                "prodCode": "S3a",
                "prodSymbolURL": "https://cards.image.pokemonkorea.co.kr/data/images/symbol/S3a.png",
                "prodName": "소드&실드 강화 확장팩 「전설의 고동」",
                "artist": "0313",
                "rarity": "C",
                "cardImgURL": "https://cards.image.pokemonkorea.co.kr/data/wmimages/S/S3a/S3a_057.png?w=512",
                "cardPageURL": "https://pokemoncard.co.kr/cards/detail/BS2020012057",
                "debug": "1"
            }
        ]
    },
    {
        "id": "S10D-053",
        "cardID": "페라무070가져000떠들030",
        "name": "페라페",
        "supertype": "포켓몬",
        "subtypes": [
            "기본"
        ],
        "rules": [],
        "hp": 70,
        "pokemons": [
            {
                "name": "페라페",
                "pokedexNumber": 441
            }
        ],
        "type": "(무색)",
        "attacks": [
            {
                "name": "가져오기",
                "cost": "(무색)",
                "damage": "",
                "text": "자신의 덱을 1장 뽑는다."
            },
            {
                "name": "떠들어대기",
                "cost": "(무색)",
                "damage": "30",
                "text": "상대의 다음 차례에 이 기술을 받은 포켓몬은 후퇴할 수 없다."
            }
        ],
        "abilities": [],
        "weakness": {
            "type": "(번개)",
            "value": "×2"
        },
        "resistance": {
            "type": "(격투)",
            "value": "-30"
        },
        "retreatCost": 1,
        "flavorText": "정교하게 인간의 말을 모사하는 재주꾼. 나이가 들어 경험이 쌓인 개체는 그 말의 의미까지 이해한다고 한다.",
        "regulationMark": [
            "F"
        ],
        "version_infos": [
            {
                "number": "053",
                "prodNumber": "067",
                "prodCode": "S10D",
                "prodSymbolURL": "https://cards.image.pokemonkorea.co.kr/data/images/symbol/S10D.png",
                "prodName": "소드&실드 확장팩 「타임게이저」",
                "artist": "Shin Nagasawa",
                "rarity": "C",
                "cardImgURL": "https://cards.image.pokemonkorea.co.kr/data/wmimages/S/S10/S10D_053.png?w=512",
                "cardPageURL": "https://pokemoncard.co.kr/cards/detail/BS2022007053",
                "debug": "1"
            }
        ]
    },
    {
        "id": "S11a-058",
        "cardID": "페라무070사이000홰치010",
        "name": "페라페",
        "supertype": "포켓몬",
        "subtypes": [
            "기본"
        ],
        "rules": [],
        "hp": 70,
        "pokemons": [
            {
                "name": "페라페",
                "pokedexNumber": 441
            }
        ],
        "type": "(무색)",
        "attacks": [
            {
                "name": "사이클드로",
                "cost": "(무색)",
                "damage": "",
                "text": "자신의 패를 1장 트래쉬한다. 그 뒤, 자신의 덱을 2장 뽑는다."
            },
            {
                "name": "홰치기",
                "cost": "(무색)",
                "damage": "10",
                "text": ""
            }
        ],
        "abilities": [],
        "weakness": {
            "type": "(번개)",
            "value": "×2"
        },
        "resistance": {
            "type": "(격투)",
            "value": "-30"
        },
        "retreatCost": 0,
        "flavorText": "사람의 말을 기억해서 운다. 동료가 한 장소에 모이면 모두 똑같은 말을 기억한다.",
        "regulationMark": [
            "F"
        ],
        "version_infos": [
            {
                "number": "058",
                "prodNumber": "068",
                "prodCode": "S11a",
                "prodSymbolURL": "https://cards.image.pokemonkorea.co.kr/data/images/symbol/S11a.png",
                "prodName": "소드&실드 강화 확장팩 「백열의 아르카나」",
                "artist": "sui",
                "rarity": "C",
                "cardImgURL": "https://cards.image.pokemonkorea.co.kr/data/wmimages/S/S11a/S11a_058.png?w=512",
                "cardPageURL": "https://pokemoncard.co.kr/cards/detail/BS2022016058",
                "debug": "1"
            }
        ]
    },
    {
        "id": "SV5K-058",
        "cardID": "페라무070아카000바람020",
        "name": "페라페",
        "supertype": "포켓몬",
        "subtypes": [
            "기본"
        ],
        "rules": [],
        "hp": 70,
        "pokemons": [
            {
                "name": "페라페",
                "pokedexNumber": 441
            }
        ],
        "type": "(무색)",
        "attacks": [
            {
                "name": "아카펠라",
                "cost": "(무색)",
                "damage": "",
                "text": "자신의 덱에서 기본 포켓몬을 3장까지 선택해서 벤치로 내보낸다. 그리고 덱을 섞는다."
            },
            {
                "name": "바람일으키기",
                "cost": "(무색)",
                "damage": "20",
                "text": ""
            }
        ],
        "abilities": [],
        "weakness": {
            "type": "(번개)",
            "value": "×2"
        },
        "resistance": {
            "type": "(격투)",
            "value": "-30"
        },
        "retreatCost": 1,
        "flavorText": "상대와 같은 울음소리를 내서 동료라고 굳게 믿게 하여 습격당하지 않도록 하고 있다.",
        "regulationMark": [
            "H"
        ],
        "version_infos": [
            {
                "number": "058",
                "prodNumber": "071",
                "prodCode": "SV5K",
                "prodSymbolURL": "https://cards.image.pokemonkorea.co.kr/data/images/symbol/SV5K.png",
                "prodName": "스칼렛&바이올렛 확장팩 「와일드포스」",
                "artist": "GOTO minori",
                "rarity": "C",
                "cardImgURL": "https://cards.image.pokemonkorea.co.kr/data/wmimages/SV/SV5K/SV5K_058.png?w=512",
                "cardPageURL": "https://pokemoncard.co.kr/cards/detail/BS2024004058",
                "debug": "1"
            },
            {
                "number": "081",
                "prodNumber": "071",
                "prodCode": "SV5K",
                "prodSymbolURL": "https://cards.image.pokemonkorea.co.kr/data/images/symbol/SV5K.png",
                "prodName": "스칼렛&바이올렛 확장팩 「와일드포스」",
                "artist": "Scav",
                "rarity": "AR",
                "cardImgURL": "https://cards.image.pokemonkorea.co.kr/data/wmimages/SV/SV5K/SV5K_081.png?w=512",
                "cardPageURL": "https://pokemoncard.co.kr/cards/detail/BS2024004081",
                "debug": "2"
            }
        ]
    },
    {
        "id": "st1-50",
        "cardID": "페라무060선취000음치010",
        "name": "페라페",
        "supertype": "포켓몬",
        "subtypes": [
            "기본"
        ],
        "rules": [],
        "hp": 60,
        "pokemons": [
            {
                "name": "페라페",
                "pokedexNumber": 441
            }
        ],
        "type": "(무색)",
        "attacks": [
            {
                "name": "선취",
                "cost": "(무색)",
                "damage": "",
                "text": "자신의 덱에서 카드를 1장 뽑는다."
            },
            {
                "name": "음치",
                "cost": "(무색)",
                "damage": "10",
                "text": "동전을 한 번 던져서 앞면이 나오면 상대를 혼란으로 만든다."
            }
        ],
        "abilities": [],
        "weakness": {
            "type": "(번개)",
            "value": "10"
        },
        "resistance": {
            "type": "(격투)",
            "value": "-20"
        },
        "retreatCost": 1,
        "flavorText": "사람의 말을 기억해서 운다. 동료가 한 장소에 모이면 모두 똑같은 말을 기억한다.",
        "regulationMark": [
            "DP"
        ],
        "version_infos": [
            {
                "number": "50",
                "prodNumber": "55",
                "prodCode": "st1",
                "prodSymbolURL": "https://cards.image.pokemonkorea.co.kr/data/images/symbol/st1.png",
                "prodName": "DP 랜덤 구축덱",
                "artist": "Ken Sugimori",
                "rarity": "N",
                "cardImgURL": "https://cards.image.pokemonkorea.co.kr/data/wmimages/DP/ST1/st1_kr_50.jpg?w=512",
                "cardPageURL": "https://pokemoncard.co.kr/cards/detail/ST2010001050",
                "debug": "1"
            }
        ]
    },
    {
        "id": "bs6-51",
        "cardID": "페라무060동료000급강030",
        "name": "페라페",
        "supertype": "포켓몬",
        "subtypes": [
            "기본"
        ],
        "rules": [],
        "hp": 60,
        "pokemons": [
            {
                "name": "페라페",
                "pokedexNumber": 441
            }
        ],
        "type": "(무색)",
        "attacks": [
            {
                "name": "동료부르기",
                "cost": "(무색)",
                "damage": "",
                "text": "자신의 덱에 있는 「기본 포켓몬」을 1장 자신의 벤치로 내보낸다. 그 뒤 덱을 섞는다."
            },
            {
                "name": "급강하",
                "cost": "(무색)(무색)",
                "damage": "30",
                "text": "동전을 한 번 던져서 뒷면이 나오면 자신에게도 10데미지를 준다."
            }
        ],
        "abilities": [],
        "weakness": {
            "type": "(번개)",
            "value": "10"
        },
        "resistance": {
            "type": "(격투)",
            "value": "-20"
        },
        "retreatCost": 1,
        "flavorText": "꽁지를 메트로놈처럼 좌우로 흔들어 리듬을 기억한다. 사람의 말을 흉내 낸다.",
        "regulationMark": [
            "DP"
        ],
        "version_infos": [
            {
                "number": "51",
                "prodNumber": "60",
                "prodCode": "bs6",
                "prodSymbolURL": "https://cards.image.pokemonkorea.co.kr/data/images/symbol/bs6.png",
                "prodName": "DP 확장팩 암흑의 초승달",
                "artist": "Satoshi Ohta",
                "rarity": "C",
                "cardImgURL": "https://cards.image.pokemonkorea.co.kr/data/wmimages/DP/BS6/bs6_ko_51.jpg?w=512",
                "cardPageURL": "https://pokemoncard.co.kr/cards/detail/BS2010006051",
                "debug": "1"
            }
        ]
    }
]