[
    {
        "id": "fsr-018",
        "cardID": "파쪼번040저리010",
        "name": "파쪼옥",
        "supertype": "포켓몬",
        "subtypes": [
            "기본"
        ],
        "rules": [],
        "hp": 40,
        "pokemons": [
            {
                "name": "파쪼옥",
                "pokedexNumber": 595
            }
        ],
        "type": "(번개)",
        "attacks": [
            {
                "name": "저리침",
                "cost": "(번개)",
                "damage": "10",
                "text": "동전을 한 번 던져서 앞면이 나오면 상대의 배틀 포켓몬을 마비로 만든다."
            }
        ],
        "abilities": [],
        "weakness": {
            "type": "(격투)",
            "value": "×2"
        },
        "resistance": {
            "type": "",
            "value": "--"
        },
        "retreatCost": 1,
        "flavorText": "몸이 큰 포켓몬에게 매달려 정전기를 빨아들인 후 축전 주머니에 전기를 모은다.",
        "regulationMark": [
            "BW"
        ],
        "version_infos": [
            {
                "number": "018",
                "prodNumber": "034",
                "prodCode": "fsr",
                "prodSymbolURL": "https://cards.image.pokemonkorea.co.kr/data/images/symbol/fsr.png",
                "prodName": "BW 「퍼스트 세트 - 불꽃의 진화」",
                "artist": "Kouki Saitou",
                "rarity": "N",
                "cardImgURL": "https://cards.image.pokemonkorea.co.kr/data/wmimages/BW/FS/bw1_fs_f_018.jpg?w=512",
                "cardPageURL": "https://pokemoncard.co.kr/cards/detail/ST2011002018",
                "debug": "1"
            }
        ]
    },
    {
        "id": "bw1w-017",
        "cardID": "파쪼번030흡혈010",
        "name": "파쪼옥",
        "supertype": "포켓몬",
        "subtypes": [
            "기본"
        ],
        "rules": [],
        "hp": 30,
        "pokemons": [
            {
                "name": "파쪼옥",
                "pokedexNumber": 595
            }
        ],
        "type": "(번개)",
        "attacks": [
            {
                "name": "흡혈",
                "cost": "(무색)",
                "damage": "10",
                "text": "상대의 배틀 포켓몬에게 준 데미지만큼 이 포켓몬의 HP를 회복한다."
            }
        ],
        "abilities": [],
        "weakness": {
            "type": "(격투)",
            "value": "×2"
        },
        "resistance": {
            "type": "",
            "value": "--"
        },
        "retreatCost": 1,
        "flavorText": "몸이 큰 포켓몬에게 매달려 정전기를 빨아들인 후 축전 주머니에 전기를 모은다.",
        "regulationMark": [
            "BW"
        ],
        "version_infos": [
            {
                "number": "017",
                "prodNumber": "053",
                "prodCode": "bw1w",
                "prodSymbolURL": "https://cards.image.pokemonkorea.co.kr/data/images/symbol/bw1w.png",
                "prodName": "BW 확장팩 제1탄 「화이트 컬렉션」",
                "artist": "Masakazu Fukuda",
                "rarity": "C",
                "cardImgURL": "https://cards.image.pokemonkorea.co.kr/data/wmimages/BW/BW1/bw1_white_017.jpg?w=512",
                "cardPageURL": "https://pokemoncard.co.kr/cards/detail/BS2011002017",
                "debug": "1"
            }
        ]
    },
    {
        "id": "bgt-001",
        "cardID": "파쪼번040갉기010",
        "name": "파쪼옥",
        "supertype": "포켓몬",
        "subtypes": [
            "기본"
        ],
        "rules": [],
        "hp": 40,
        "pokemons": [
            {
                "name": "파쪼옥",
                "pokedexNumber": 595
            }
        ],
        "type": "(번개)",
        "attacks": [
            {
                "name": "갉기",
                "cost": "(무색)",
                "damage": "10",
                "text": ""
            }
        ],
        "abilities": [],
        "weakness": {
            "type": "(격투)",
            "value": "×2"
        },
        "resistance": {
            "type": "",
            "value": "--"
        },
        "retreatCost": 1,
        "flavorText": "거리에서 사는 파쪼옥은 민가의 콘센트에서 전기를 빨아들이는 방법을 알고 있다.",
        "regulationMark": [
            "BW"
        ],
        "version_infos": [
            {
                "number": "001",
                "prodNumber": "014",
                "prodCode": "bgt",
                "prodSymbolURL": "https://cards.image.pokemonkorea.co.kr/data/images/symbol/bgt.png",
                "prodName": "BW 「배틀 강화덱 - 테라키온 덱」",
                "artist": "Kagemaru Himeno",
                "rarity": "N",
                "cardImgURL": "https://cards.image.pokemonkorea.co.kr/data/wmimages/BW/BG_terrakion/bw1_terrakion_001.jpg?w=512",
                "cardPageURL": "https://pokemoncard.co.kr/cards/detail/ST2011005001",
                "debug": "1"
            }
        ]
    },
    {
        "id": "bw4-028",
        "cardID": "파쪼번030찌릿020",
        "name": "파쪼옥",
        "supertype": "포켓몬",
        "subtypes": [
            "기본"
        ],
        "rules": [],
        "hp": 30,
        "pokemons": [
            {
                "name": "파쪼옥",
                "pokedexNumber": 595
            }
        ],
        "type": "(번개)",
        "attacks": [
            {
                "name": "찌릿찌릿",
                "cost": "(번개)",
                "damage": "20",
                "text": ""
            }
        ],
        "abilities": [],
        "weakness": {
            "type": "(격투)",
            "value": "×2"
        },
        "resistance": {
            "type": "",
            "value": "--"
        },
        "retreatCost": 1,
        "flavorText": "몸이 큰 포켓몬에게 매달려 정전기를 빨아들인 후 축전 주머니에 전기를 모은다.",
        "regulationMark": [
            "BW"
        ],
        "version_infos": [
            {
                "number": "028",
                "prodNumber": "069",
                "prodCode": "bw4",
                "prodSymbolURL": "https://cards.image.pokemonkorea.co.kr/data/images/symbol/bw4.png",
                "prodName": "BW 확장팩 제4탄 「다크러시」",
                "artist": "Miki Tanaka",
                "rarity": "C",
                "cardImgURL": "https://cards.image.pokemonkorea.co.kr/data/wmimages/BW/BGR/bw4_028.jpg?w=512",
                "cardPageURL": "https://pokemoncard.co.kr/cards/detail/BS2012003028",
                "debug": "1"
            }
        ]
    },
    {
        "id": "bd-001",
        "cardID": "파쪼번030부딪010벌래020",
        "name": "파쪼옥",
        "supertype": "포켓몬",
        "subtypes": [
            "기본"
        ],
        "rules": [],
        "hp": 30,
        "pokemons": [
            {
                "name": "파쪼옥",
                "pokedexNumber": 595
            }
        ],
        "type": "(번개)",
        "attacks": [
            {
                "name": "부딪치기",
                "cost": "(무색)",
                "damage": "10",
                "text": ""
            },
            {
                "name": "벌래먹음",
                "cost": "(무색)(무색)",
                "damage": "20",
                "text": ""
            }
        ],
        "abilities": [],
        "weakness": {
            "type": "(격투)",
            "value": "×2"
        },
        "resistance": {
            "type": "",
            "value": "--"
        },
        "retreatCost": 1,
        "flavorText": "몸이 큰 포켓몬에게 매달려 정전기를 빨아들인 후 축전 주머니에 전기를 모은다.",
        "regulationMark": [
            "BW"
        ],
        "version_infos": [
            {
                "number": "001",
                "prodNumber": "013",
                "prodCode": "bd",
                "prodSymbolURL": "https://cards.image.pokemonkorea.co.kr/data/images/symbol/bd.png",
                "prodName": "BW 「볼트로스 덱」",
                "artist": "MAHOU",
                "rarity": "N",
                "cardImgURL": "https://cards.image.pokemonkorea.co.kr/data/wmimages/BW/BD/bw_bd_001.jpg?w=512",
                "cardPageURL": "https://pokemoncard.co.kr/cards/detail/ST2012004001",
                "debug": "3"
            }
        ]
    },
    {
        "id": "bw6c-022",
        "cardID": "파쪼번040달려010",
        "name": "파쪼옥",
        "supertype": "포켓몬",
        "subtypes": [
            "기본"
        ],
        "rules": [],
        "hp": 40,
        "pokemons": [
            {
                "name": "파쪼옥",
                "pokedexNumber": 595
            }
        ],
        "type": "(번개)",
        "attacks": [
            {
                "name": "달려들기",
                "cost": "(번개)",
                "damage": "10+",
                "text": "동전을 한 번 던져서 앞면이 나오면 10데미지를 추가한다."
            }
        ],
        "abilities": [],
        "weakness": {
            "type": "(격투)",
            "value": "×2"
        },
        "resistance": {
            "type": "",
            "value": "--"
        },
        "retreatCost": 1,
        "flavorText": "스스로 전기를 만들 수 없어 다른 큰 포켓몬에 달라붙어 정전기를 흡수한다.",
        "regulationMark": [
            "BW"
        ],
        "version_infos": [
            {
                "number": "022",
                "prodNumber": "059",
                "prodCode": "bw6c",
                "prodSymbolURL": "https://cards.image.pokemonkorea.co.kr/data/images/symbol/bw6c.png",
                "prodName": "BW 확장팩 제6탄 「콜드플레어」",
                "artist": "Tomokazu Komiya",
                "rarity": "C",
                "cardImgURL": "https://cards.image.pokemonkorea.co.kr/data/wmimages/BW/BW6/bw6_coldflare_022.jpg?w=512",
                "cardPageURL": "https://pokemoncard.co.kr/cards/detail/BS2012009022",
                "debug": "1"
            }
        ]
    },
    {
        "id": "xy4-026",
        "cardID": "파쪼번030갉기010밤의020",
        "name": "파쪼옥",
        "supertype": "포켓몬",
        "subtypes": [
            "기본"
        ],
        "rules": [],
        "hp": 30,
        "pokemons": [
            {
                "name": "파쪼옥",
                "pokedexNumber": 595
            }
        ],
        "type": "(번개)",
        "attacks": [
            {
                "name": "갉기",
                "cost": "(번개)",
                "damage": "10",
                "text": ""
            },
            {
                "name": "밤의행진",
                "cost": "(무색)(무색)",
                "damage": "20×",
                "text": "자신의 트래쉬에 있는 기술 「밤의행진」을 가진 포켓몬의 장수 × 20데미지를 준다."
            }
        ],
        "abilities": [],
        "weakness": {
            "type": "(격투)",
            "value": "×2"
        },
        "resistance": {
            "type": "(강철)",
            "value": "-20"
        },
        "retreatCost": 1,
        "flavorText": "스스로 전기를 만들 수 없어 다른 큰 포켓몬에 달라붙어 정전기를 흡수한다.",
        "regulationMark": [
            "XY"
        ],
        "version_infos": [
            {
                "number": "026",
                "prodNumber": "088",
                "prodCode": "xy4",
                "prodSymbolURL": "https://cards.image.pokemonkorea.co.kr/data/images/symbol/xy4.png",
                "prodName": "XY 확장팩 제4탄 「팬텀게이트」",
                "artist": "TOKIYA",
                "rarity": "C",
                "cardImgURL": "https://cards.image.pokemonkorea.co.kr/data/wmimages/XY/XY4/XY4_026.jpg?w=512",
                "cardPageURL": "https://pokemoncard.co.kr/cards/detail/BS2014004026",
                "debug": "1"
            },
            {
                "number": "044",
                "prodNumber": "131",
                "prodCode": "cp4",
                "prodSymbolURL": "https://cards.image.pokemonkorea.co.kr/data/images/symbol/cp4.png",
                "prodName": "XY BREAK 확장팩 「프리미엄 챔피언팩」",
                "artist": "TOKIYA",
                "rarity": "N",
                "cardImgURL": "https://cards.image.pokemonkorea.co.kr/data/wmimages/XY/CP4/CP4_044.jpg?w=512",
                "cardPageURL": "https://pokemoncard.co.kr/cards/detail/BS2016004044",
                "debug": "2"
            },
            {
                "number": "036",
                "prodNumber": "171",
                "prodCode": "smxy",
                "prodSymbolURL": "https://cards.image.pokemonkorea.co.kr/data/images/symbol/smxy.png",
                "prodName": "하이클래스팩 「THE BEST OF XY」",
                "artist": "TOKIYA",
                "rarity": "N",
                "cardImgURL": "https://cards.image.pokemonkorea.co.kr/data/wmimages/SM/SMXY/SMXY_036.png?w=512",
                "cardPageURL": "https://pokemoncard.co.kr/cards/detail/BS201707036",
                "debug": "2"
            }
        ]
    },
    {
        "id": "xy11b-021",
        "cardID": "파쪼번030들러010",
        "name": "파쪼옥",
        "supertype": "포켓몬",
        "subtypes": [
            "기본"
        ],
        "rules": [],
        "hp": 30,
        "pokemons": [
            {
                "name": "파쪼옥",
                "pokedexNumber": 595
            }
        ],
        "type": "(번개)",
        "attacks": [
            {
                "name": "들러붙기",
                "cost": "(번개)",
                "damage": "10",
                "text": ""
            }
        ],
        "abilities": [],
        "weakness": {
            "type": "(격투)",
            "value": "×2"
        },
        "resistance": {
            "type": "(강철)",
            "value": "-20"
        },
        "retreatCost": 0,
        "flavorText": "몸이 큰 포켓몬에게 매달려 정전기를 빨아들인 후 축전 주머니에 전기를 모은다.",
        "regulationMark": [
            "XY"
        ],
        "version_infos": [
            {
                "number": "021",
                "prodNumber": "054",
                "prodCode": "xy11b",
                "prodSymbolURL": "https://cards.image.pokemonkorea.co.kr/data/images/symbol/xy11b.png",
                "prodName": "XY BREAK 확장팩 제11탄 「타오르는 투사」",
                "artist": "Ayaka Yoshida",
                "rarity": "C",
                "cardImgURL": "https://cards.image.pokemonkorea.co.kr/data/wmimages/XY/XY11/XY11A_021.jpg?w=512",
                "cardPageURL": "https://pokemoncard.co.kr/cards/detail/BS2016006021",
                "debug": "1"
            }
        ]
    },
    {
        "id": "sm8a-010",
        "cardID": "파쪼번040흡혈010",
        "name": "파쪼옥",
        "supertype": "포켓몬",
        "subtypes": [
            "기본"
        ],
        "rules": [],
        "hp": 40,
        "pokemons": [
            {
                "name": "파쪼옥",
                "pokedexNumber": 595
            }
        ],
        "type": "(번개)",
        "attacks": [
            {
                "name": "흡혈",
                "cost": "(번개)",
                "damage": "10",
                "text": "상대의 배틀 포켓몬에게 준 데미지만큼 이 포켓몬의 HP를 회복한다."
            }
        ],
        "abilities": [],
        "weakness": {
            "type": "(격투)",
            "value": "×2"
        },
        "resistance": {
            "type": "(강철)",
            "value": "-20"
        },
        "retreatCost": 1,
        "flavorText": "몸이 큰 포켓몬에게 매달려 정전기를 빨아들인 후 축전 주머니에 전기를 모은다.",
        "regulationMark": [
            "B"
        ],
        "version_infos": [
            {
                "number": "010",
                "prodNumber": "052",
                "prodCode": "sm8a",
                "prodSymbolURL": "https://cards.image.pokemonkorea.co.kr/data/images/symbol/sm8a.png",
                "prodName": "썬&문 강화 확장팩 「다크오더」",
                "artist": "Yuka Morii",
                "rarity": "C",
                "cardImgURL": "https://cards.image.pokemonkorea.co.kr/data/wmimages/SM/SM8A/SM8a_010.png?w=512",
                "cardPageURL": "https://pokemoncard.co.kr/cards/detail/BS2018013010",
                "debug": "1"
            },
            {
                "number": "010",
                "prodNumber": "052",
                "prodCode": "sm8a",
                "prodSymbolURL": "https://cards.image.pokemonkorea.co.kr/data/images/symbol/sm8a.png",
                "prodName": "썬&문 강화 확장팩 「다크오더」",
                "artist": "Yuka Morii",
                "rarity": "C",
                "cardImgURL": "https://cards.image.pokemonkorea.co.kr/data/wmimages/SM/SM8A/SM8a_066.png?w=512",
                "cardPageURL": "https://pokemoncard.co.kr/cards/detail/BS2018013066",
                "debug": "2"
            }
        ]
    },
    {
        "id": "SM11-022",
        "cardID": "파쪼번040프티000",
        "name": "파쪼옥",
        "supertype": "포켓몬",
        "subtypes": [
            "기본"
        ],
        "rules": [],
        "hp": 40,
        "pokemons": [
            {
                "name": "파쪼옥",
                "pokedexNumber": 595
            }
        ],
        "type": "(번개)",
        "attacks": [
            {
                "name": "프티쇼크",
                "cost": "(무색)",
                "damage": "",
                "text": "동전을 1번 던져서 앞면이 나오면 상대의 배틀 포켓몬을 마비로 만든다."
            }
        ],
        "abilities": [],
        "weakness": {
            "type": "(격투)",
            "value": "×2"
        },
        "resistance": {
            "type": "(강철)",
            "value": "-20"
        },
        "retreatCost": 1,
        "flavorText": "스스로 전기를 만들 수 없어 다른 큰 포켓몬에 달라붙어 정전기를 흡수한다.",
        "regulationMark": [
            "C"
        ],
        "version_infos": [
            {
                "number": "022",
                "prodNumber": "094",
                "prodCode": "SM11",
                "prodSymbolURL": "https://cards.image.pokemonkorea.co.kr/data/images/symbol/SM11.png",
                "prodName": "썬&문 확장팩 제11탄 「미라클트윈」",
                "artist": "Midori Harada",
                "rarity": "C",
                "cardImgURL": "https://cards.image.pokemonkorea.co.kr/data/wmimages/SM/SM11/SM11_022.png?w=512",
                "cardPageURL": "https://pokemoncard.co.kr/cards/detail/BS2019013022",
                "debug": "1"
            }
        ]
    },
    {
        "id": "SA_L-004",
        "cardID": "파쪼번050돌아010",
        "name": "파쪼옥",
        "supertype": "포켓몬",
        "subtypes": [
            "기본"
        ],
        "rules": [],
        "hp": 50,
        "pokemons": [
            {
                "name": "파쪼옥",
                "pokedexNumber": 595
            }
        ],
        "type": "(번개)",
        "attacks": [
            {
                "name": "돌아다니며 뛰기",
                "cost": "(번개)",
                "damage": "10",
                "text": ""
            }
        ],
        "abilities": [],
        "weakness": {
            "type": "(격투)",
            "value": "×2"
        },
        "resistance": {
            "type": "",
            "value": "--"
        },
        "retreatCost": 1,
        "flavorText": "포켓몬의 몸에 들러붙어 정전기를 흡수한다. 스스로는 전기를 만들 수 없다.",
        "regulationMark": [
            "D"
        ],
        "version_infos": [
            {
                "number": "004",
                "prodNumber": "024",
                "prodCode": "SA_L",
                "prodSymbolURL": "https://cards.image.pokemonkorea.co.kr/data/images/symbol/SA_L.png",
                "prodName": "소드&실드 스타터 세트 V 번개",
                "artist": "Motofumi Fujiwara",
                "rarity": "N",
                "cardImgURL": "https://cards.image.pokemonkorea.co.kr/data/wmimages/S/SA/SA_L_004.png?w=512",
                "cardPageURL": "https://pokemoncard.co.kr/cards/detail/BS2020001076",
                "debug": "1"
            }
        ]
    },
    {
        "id": "S3a-018",
        "cardID": "파쪼번040벌레020",
        "name": "파쪼옥",
        "supertype": "포켓몬",
        "subtypes": [
            "기본"
        ],
        "rules": [],
        "hp": 40,
        "pokemons": [
            {
                "name": "파쪼옥",
                "pokedexNumber": 595
            }
        ],
        "type": "(번개)",
        "attacks": [
            {
                "name": "벌레먹음",
                "cost": "(번개)",
                "damage": "20",
                "text": ""
            }
        ],
        "abilities": [],
        "weakness": {
            "type": "(격투)",
            "value": "×2"
        },
        "resistance": {
            "type": "",
            "value": "--"
        },
        "retreatCost": 1,
        "flavorText": "포켓몬의 몸에 들러붙어 정전기를 흡수한다. 스스로는 전기를 만들 수 없다.",
        "regulationMark": [
            "D"
        ],
        "version_infos": [
            {
                "number": "018",
                "prodNumber": "076",
                "prodCode": "S3a",
                "prodSymbolURL": "https://cards.image.pokemonkorea.co.kr/data/images/symbol/S3a.png",
                "prodName": "소드&실드 강화 확장팩 「전설의 고동」",
                "artist": "Sumiyoshi Kizuki",
                "rarity": "C",
                "cardImgURL": "https://cards.image.pokemonkorea.co.kr/data/wmimages/S/S3a/S3a_018.png?w=512",
                "cardPageURL": "https://pokemoncard.co.kr/cards/detail/BS2020012018",
                "debug": "1"
            }
        ]
    },
    {
        "id": "SV3a-016",
        "cardID": "파쪼번040마구010",
        "name": "파쪼옥",
        "supertype": "포켓몬",
        "subtypes": [
            "기본"
        ],
        "rules": [],
        "hp": 40,
        "pokemons": [
            {
                "name": "파쪼옥",
                "pokedexNumber": 595
            }
        ],
        "type": "(번개)",
        "attacks": [
            {
                "name": "마구 튀기",
                "cost": "(번개)",
                "damage": "10×",
                "text": "동전을 3번 던져서 앞면이 나온 수 × 10데미지를 준다."
            }
        ],
        "abilities": [],
        "weakness": {
            "type": "(격투)",
            "value": "×2"
        },
        "resistance": {
            "type": "",
            "value": "--"
        },
        "retreatCost": 1,
        "flavorText": "다른 포켓몬에게 달라붙어 정전기를 빨아들인다. 멍파치의 엉덩이에 자주 달라붙어 있다.",
        "regulationMark": [
            "G"
        ],
        "version_infos": [
            {
                "number": "016",
                "prodNumber": "062",
                "prodCode": "SV3a",
                "prodSymbolURL": "https://cards.image.pokemonkorea.co.kr/data/images/symbol/SV3a.png",
                "prodName": "스칼렛&바이올렛 강화 확장팩 「레이징서프」",
                "artist": "Kedamahadaitai Yawarakai",
                "rarity": "C",
                "cardImgURL": "https://cards.image.pokemonkorea.co.kr/data/wmimages/SV/SV3a/SV3a_016.png?w=512",
                "cardPageURL": "https://pokemoncard.co.kr/cards/detail/BS2023020016",
                "debug": "1"
            },
            {
                "number": "067",
                "prodNumber": "062",
                "prodCode": "SV3a",
                "prodSymbolURL": "https://cards.image.pokemonkorea.co.kr/data/images/symbol/SV3a.png",
                "prodName": "스칼렛&바이올렛 강화 확장팩 「레이징서프」",
                "artist": "Atsushi Furusawa",
                "rarity": "AR",
                "cardImgURL": "https://cards.image.pokemonkorea.co.kr/data/wmimages/SV/SV3a/SV3a_067.png?w=512",
                "cardPageURL": "https://pokemoncard.co.kr/cards/detail/BS2023020067",
                "debug": "2"
            }
        ]
    }
]